{
  "AllergyIntolerance": [
    {
      "name": "identifier",
      "path": "AllergyIntolerance.identifier"
    },
    {
      "name": "clinicalStatus",
      "path": "AllergyIntolerance.clinicalStatus"
    },
    {
      "name": "verificationStatus",
      "path": "AllergyIntolerance.verificationStatus"
    },
    {
      "name": "type",
      "path": "AllergyIntolerance.type"
    },
    {
      "name": "category",
      "path": "AllergyIntolerance.category"
    },
    {
      "name": "criticality",
      "path": "AllergyIntolerance.criticality"
    },
    {
      "name": "code",
      "path": "AllergyIntolerance.code"
    },
    {
      "name": "patient",
      "path": "AllergyIntolerance.patient"
    },
    {
      "name": "onsetDateTime",
      "path": "AllergyIntolerance.onsetDateTime"
    },
    {
      "name": "onsetAge",
      "path": "AllergyIntolerance.onsetAge"
    },
    {
      "name": "onsetPeriod",
      "path": "AllergyIntolerance.onsetPeriod"
    },
    {
      "name": "onsetRange",
      "path": "AllergyIntolerance.onsetRange"
    },
    {
      "name": "onsetString",
      "path": "AllergyIntolerance.onsetString"
    },
    {
      "name": "assertedDate",
      "path": "AllergyIntolerance.assertedDate"
    },
    {
      "name": "recorder",
      "path": "AllergyIntolerance.recorder"
    },
    {
      "name": "asserter",
      "path": "AllergyIntolerance.asserter"
    },
    {
      "name": "lastOccurrence",
      "path": "AllergyIntolerance.lastOccurrence"
    },
    {
      "name": "note",
      "path": "AllergyIntolerance.note"
    },
    {
      "name": "reaction",
      "path": "AllergyIntolerance.reaction",
      "children": [
        {
          "name": "substance",
          "path": "AllergyIntolerance.reaction.substance"
        },
        {
          "name": "manifestation",
          "path": "AllergyIntolerance.reaction.manifestation"
        },
        {
          "name": "description",
          "path": "AllergyIntolerance.reaction.description"
        },
        {
          "name": "onset",
          "path": "AllergyIntolerance.reaction.onset"
        },
        {
          "name": "severity",
          "path": "AllergyIntolerance.reaction.severity"
        },
        {
          "name": "exposureRoute",
          "path": "AllergyIntolerance.reaction.exposureRoute"
        },
        {
          "name": "note",
          "path": "AllergyIntolerance.reaction.note"
        }
      ]
    }
  ],
  "CarePlan": [
    {
      "name": "identifier",
      "path": "CarePlan.identifier"
    },
    {
      "name": "definition",
      "path": "CarePlan.definition"
    },
    {
      "name": "basedOn",
      "path": "CarePlan.basedOn"
    },
    {
      "name": "replaces",
      "path": "CarePlan.replaces"
    },
    {
      "name": "partOf",
      "path": "CarePlan.partOf"
    },
    {
      "name": "status",
      "path": "CarePlan.status"
    },
    {
      "name": "intent",
      "path": "CarePlan.intent"
    },
    {
      "name": "category",
      "path": "CarePlan.category"
    },
    {
      "name": "title",
      "path": "CarePlan.title"
    },
    {
      "name": "description",
      "path": "CarePlan.description"
    },
    {
      "name": "subject",
      "path": "CarePlan.subject"
    },
    {
      "name": "context",
      "path": "CarePlan.context"
    },
    {
      "name": "period",
      "path": "CarePlan.period"
    },
    {
      "name": "author",
      "path": "CarePlan.author"
    },
    {
      "name": "careTeam",
      "path": "CarePlan.careTeam"
    },
    {
      "name": "addresses",
      "path": "CarePlan.addresses"
    },
    {
      "name": "supportingInfo",
      "path": "CarePlan.supportingInfo"
    },
    {
      "name": "goal",
      "path": "CarePlan.goal"
    },
    {
      "name": "activity",
      "path": "CarePlan.activity",
      "children": [
        {
          "name": "outcomeCodeableConcept",
          "path": "CarePlan.activity.outcomeCodeableConcept"
        },
        {
          "name": "outcomeReference",
          "path": "CarePlan.activity.outcomeReference"
        },
        {
          "name": "progress",
          "path": "CarePlan.activity.progress"
        },
        {
          "name": "reference",
          "path": "CarePlan.activity.reference"
        },
        {
          "name": "detail",
          "path": "CarePlan.activity.detail",
          "children": [
            {
              "name": "category",
              "path": "CarePlan.activity.detail.category"
            },
            {
              "name": "definition",
              "path": "CarePlan.activity.detail.definition"
            },
            {
              "name": "code",
              "path": "CarePlan.activity.detail.code"
            },
            {
              "name": "reasonCode",
              "path": "CarePlan.activity.detail.reasonCode"
            },
            {
              "name": "reasonReference",
              "path": "CarePlan.activity.detail.reasonReference"
            },
            {
              "name": "goal",
              "path": "CarePlan.activity.detail.goal"
            },
            {
              "name": "status",
              "path": "CarePlan.activity.detail.status"
            },
            {
              "name": "statusReason",
              "path": "CarePlan.activity.detail.statusReason"
            },
            {
              "name": "prohibited",
              "path": "CarePlan.activity.detail.prohibited"
            },
            {
              "name": "scheduledTiming",
              "path": "CarePlan.activity.detail.scheduledTiming"
            },
            {
              "name": "scheduledPeriod",
              "path": "CarePlan.activity.detail.scheduledPeriod"
            },
            {
              "name": "scheduledString",
              "path": "CarePlan.activity.detail.scheduledString"
            },
            {
              "name": "location",
              "path": "CarePlan.activity.detail.location"
            },
            {
              "name": "performer",
              "path": "CarePlan.activity.detail.performer"
            },
            {
              "name": "productCodeableConcept",
              "path": "CarePlan.activity.detail.productCodeableConcept"
            },
            {
              "name": "productReference",
              "path": "CarePlan.activity.detail.productReference"
            },
            {
              "name": "dailyAmount",
              "path": "CarePlan.activity.detail.dailyAmount"
            },
            {
              "name": "quantity",
              "path": "CarePlan.activity.detail.quantity"
            },
            {
              "name": "description",
              "path": "CarePlan.activity.detail.description"
            }
          ]
        }
      ]
    },
    {
      "name": "note",
      "path": "CarePlan.note"
    }
  ],
  "Claim": [
    {
      "name": "identifier",
      "path": "Claim.identifier"
    },
    {
      "name": "status",
      "path": "Claim.status"
    },
    {
      "name": "type",
      "path": "Claim.type"
    },
    {
      "name": "subType",
      "path": "Claim.subType"
    },
    {
      "name": "use",
      "path": "Claim.use"
    },
    {
      "name": "patient",
      "path": "Claim.patient"
    },
    {
      "name": "billablePeriod",
      "path": "Claim.billablePeriod"
    },
    {
      "name": "created",
      "path": "Claim.created"
    },
    {
      "name": "enterer",
      "path": "Claim.enterer"
    },
    {
      "name": "insurer",
      "path": "Claim.insurer"
    },
    {
      "name": "provider",
      "path": "Claim.provider"
    },
    {
      "name": "organization",
      "path": "Claim.organization"
    },
    {
      "name": "priority",
      "path": "Claim.priority"
    },
    {
      "name": "fundsReserve",
      "path": "Claim.fundsReserve"
    },
    {
      "name": "related",
      "path": "Claim.related",
      "children": [
        {
          "name": "claim",
          "path": "Claim.related.claim"
        },
        {
          "name": "relationship",
          "path": "Claim.related.relationship"
        },
        {
          "name": "reference",
          "path": "Claim.related.reference"
        }
      ]
    },
    {
      "name": "prescription",
      "path": "Claim.prescription"
    },
    {
      "name": "originalPrescription",
      "path": "Claim.originalPrescription"
    },
    {
      "name": "payee",
      "path": "Claim.payee",
      "children": [
        {
          "name": "type",
          "path": "Claim.payee.type"
        },
        {
          "name": "resourceType",
          "path": "Claim.payee.resourceType"
        },
        {
          "name": "party",
          "path": "Claim.payee.party"
        }
      ]
    },
    {
      "name": "referral",
      "path": "Claim.referral"
    },
    {
      "name": "facility",
      "path": "Claim.facility"
    },
    {
      "name": "careTeam",
      "path": "Claim.careTeam",
      "children": [
        {
          "name": "sequence",
          "path": "Claim.careTeam.sequence"
        },
        {
          "name": "provider",
          "path": "Claim.careTeam.provider"
        },
        {
          "name": "responsible",
          "path": "Claim.careTeam.responsible"
        },
        {
          "name": "role",
          "path": "Claim.careTeam.role"
        },
        {
          "name": "qualification",
          "path": "Claim.careTeam.qualification"
        }
      ]
    },
    {
      "name": "information",
      "path": "Claim.information",
      "children": [
        {
          "name": "sequence",
          "path": "Claim.information.sequence"
        },
        {
          "name": "category",
          "path": "Claim.information.category"
        },
        {
          "name": "code",
          "path": "Claim.information.code"
        },
        {
          "name": "timingDate",
          "path": "Claim.information.timingDate"
        },
        {
          "name": "timingPeriod",
          "path": "Claim.information.timingPeriod"
        },
        {
          "name": "valueString",
          "path": "Claim.information.valueString"
        },
        {
          "name": "valueQuantity",
          "path": "Claim.information.valueQuantity"
        },
        {
          "name": "valueAttachment",
          "path": "Claim.information.valueAttachment"
        },
        {
          "name": "valueReference",
          "path": "Claim.information.valueReference"
        },
        {
          "name": "reason",
          "path": "Claim.information.reason"
        }
      ]
    },
    {
      "name": "diagnosis",
      "path": "Claim.diagnosis",
      "children": [
        {
          "name": "sequence",
          "path": "Claim.diagnosis.sequence"
        },
        {
          "name": "diagnosisCodeableConcept",
          "path": "Claim.diagnosis.diagnosisCodeableConcept"
        },
        {
          "name": "diagnosisReference",
          "path": "Claim.diagnosis.diagnosisReference"
        },
        {
          "name": "type",
          "path": "Claim.diagnosis.type"
        },
        {
          "name": "packageCode",
          "path": "Claim.diagnosis.packageCode"
        }
      ]
    },
    {
      "name": "procedure",
      "path": "Claim.procedure",
      "children": [
        {
          "name": "sequence",
          "path": "Claim.procedure.sequence"
        },
        {
          "name": "date",
          "path": "Claim.procedure.date"
        },
        {
          "name": "procedureCodeableConcept",
          "path": "Claim.procedure.procedureCodeableConcept"
        },
        {
          "name": "procedureReference",
          "path": "Claim.procedure.procedureReference"
        }
      ]
    },
    {
      "name": "insurance",
      "path": "Claim.insurance",
      "children": [
        {
          "name": "sequence",
          "path": "Claim.insurance.sequence"
        },
        {
          "name": "focal",
          "path": "Claim.insurance.focal"
        },
        {
          "name": "coverage",
          "path": "Claim.insurance.coverage"
        },
        {
          "name": "businessArrangement",
          "path": "Claim.insurance.businessArrangement"
        },
        {
          "name": "preAuthRef",
          "path": "Claim.insurance.preAuthRef"
        },
        {
          "name": "claimResponse",
          "path": "Claim.insurance.claimResponse"
        }
      ]
    },
    {
      "name": "accident",
      "path": "Claim.accident",
      "children": [
        {
          "name": "date",
          "path": "Claim.accident.date"
        },
        {
          "name": "type",
          "path": "Claim.accident.type"
        },
        {
          "name": "locationAddress",
          "path": "Claim.accident.locationAddress"
        },
        {
          "name": "locationReference",
          "path": "Claim.accident.locationReference"
        }
      ]
    },
    {
      "name": "employmentImpacted",
      "path": "Claim.employmentImpacted"
    },
    {
      "name": "hospitalization",
      "path": "Claim.hospitalization"
    },
    {
      "name": "item",
      "path": "Claim.item",
      "children": [
        {
          "name": "sequence",
          "path": "Claim.item.sequence"
        },
        {
          "name": "careTeamLinkId",
          "path": "Claim.item.careTeamLinkId"
        },
        {
          "name": "diagnosisLinkId",
          "path": "Claim.item.diagnosisLinkId"
        },
        {
          "name": "procedureLinkId",
          "path": "Claim.item.procedureLinkId"
        },
        {
          "name": "informationLinkId",
          "path": "Claim.item.informationLinkId"
        },
        {
          "name": "revenue",
          "path": "Claim.item.revenue"
        },
        {
          "name": "category",
          "path": "Claim.item.category"
        },
        {
          "name": "service",
          "path": "Claim.item.service"
        },
        {
          "name": "modifier",
          "path": "Claim.item.modifier"
        },
        {
          "name": "programCode",
          "path": "Claim.item.programCode"
        },
        {
          "name": "servicedDate",
          "path": "Claim.item.servicedDate"
        },
        {
          "name": "servicedPeriod",
          "path": "Claim.item.servicedPeriod"
        },
        {
          "name": "locationCodeableConcept",
          "path": "Claim.item.locationCodeableConcept"
        },
        {
          "name": "locationAddress",
          "path": "Claim.item.locationAddress"
        },
        {
          "name": "locationReference",
          "path": "Claim.item.locationReference"
        },
        {
          "name": "quantity",
          "path": "Claim.item.quantity"
        },
        {
          "name": "unitPrice",
          "path": "Claim.item.unitPrice"
        },
        {
          "name": "factor",
          "path": "Claim.item.factor"
        },
        {
          "name": "net",
          "path": "Claim.item.net"
        },
        {
          "name": "udi",
          "path": "Claim.item.udi"
        },
        {
          "name": "bodySite",
          "path": "Claim.item.bodySite"
        },
        {
          "name": "subSite",
          "path": "Claim.item.subSite"
        },
        {
          "name": "encounter",
          "path": "Claim.item.encounter"
        },
        {
          "name": "detail",
          "path": "Claim.item.detail",
          "children": [
            {
              "name": "sequence",
              "path": "Claim.item.detail.sequence"
            },
            {
              "name": "revenue",
              "path": "Claim.item.detail.revenue"
            },
            {
              "name": "category",
              "path": "Claim.item.detail.category"
            },
            {
              "name": "service",
              "path": "Claim.item.detail.service"
            },
            {
              "name": "modifier",
              "path": "Claim.item.detail.modifier"
            },
            {
              "name": "programCode",
              "path": "Claim.item.detail.programCode"
            },
            {
              "name": "quantity",
              "path": "Claim.item.detail.quantity"
            },
            {
              "name": "unitPrice",
              "path": "Claim.item.detail.unitPrice"
            },
            {
              "name": "factor",
              "path": "Claim.item.detail.factor"
            },
            {
              "name": "net",
              "path": "Claim.item.detail.net"
            },
            {
              "name": "udi",
              "path": "Claim.item.detail.udi"
            },
            {
              "name": "subDetail",
              "path": "Claim.item.detail.subDetail",
              "children": [
                {
                  "name": "sequence",
                  "path": "Claim.item.detail.subDetail.sequence"
                },
                {
                  "name": "revenue",
                  "path": "Claim.item.detail.subDetail.revenue"
                },
                {
                  "name": "category",
                  "path": "Claim.item.detail.subDetail.category"
                },
                {
                  "name": "service",
                  "path": "Claim.item.detail.subDetail.service"
                },
                {
                  "name": "modifier",
                  "path": "Claim.item.detail.subDetail.modifier"
                },
                {
                  "name": "programCode",
                  "path": "Claim.item.detail.subDetail.programCode"
                },
                {
                  "name": "quantity",
                  "path": "Claim.item.detail.subDetail.quantity"
                },
                {
                  "name": "unitPrice",
                  "path": "Claim.item.detail.subDetail.unitPrice"
                },
                {
                  "name": "factor",
                  "path": "Claim.item.detail.subDetail.factor"
                },
                {
                  "name": "net",
                  "path": "Claim.item.detail.subDetail.net"
                },
                {
                  "name": "udi",
                  "path": "Claim.item.detail.subDetail.udi"
                }
              ]
            }
          ]
        }
      ]
    },
    {
      "name": "total",
      "path": "Claim.total"
    }
  ],
  "Condition": [
    {
      "name": "identifier",
      "path": "Condition.identifier"
    },
    {
      "name": "clinicalStatus",
      "path": "Condition.clinicalStatus"
    },
    {
      "name": "verificationStatus",
      "path": "Condition.verificationStatus"
    },
    {
      "name": "category",
      "path": "Condition.category"
    },
    {
      "name": "severity",
      "path": "Condition.severity"
    },
    {
      "name": "code",
      "path": "Condition.code"
    },
    {
      "name": "bodySite",
      "path": "Condition.bodySite"
    },
    {
      "name": "subject",
      "path": "Condition.subject"
    },
    {
      "name": "context",
      "path": "Condition.context"
    },
    {
      "name": "onsetDateTime",
      "path": "Condition.onsetDateTime"
    },
    {
      "name": "onsetAge",
      "path": "Condition.onsetAge"
    },
    {
      "name": "onsetPeriod",
      "path": "Condition.onsetPeriod"
    },
    {
      "name": "onsetRange",
      "path": "Condition.onsetRange"
    },
    {
      "name": "onsetString",
      "path": "Condition.onsetString"
    },
    {
      "name": "abatementDateTime",
      "path": "Condition.abatementDateTime"
    },
    {
      "name": "abatementAge",
      "path": "Condition.abatementAge"
    },
    {
      "name": "abatementBoolean",
      "path": "Condition.abatementBoolean"
    },
    {
      "name": "abatementPeriod",
      "path": "Condition.abatementPeriod"
    },
    {
      "name": "abatementRange",
      "path": "Condition.abatementRange"
    },
    {
      "name": "abatementString",
      "path": "Condition.abatementString"
    },
    {
      "name": "assertedDate",
      "path": "Condition.assertedDate"
    },
    {
      "name": "asserter",
      "path": "Condition.asserter"
    },
    {
      "name": "stage",
      "path": "Condition.stage",
      "children": [
        {
          "name": "summary",
          "path": "Condition.stage.summary"
        },
        {
          "name": "assessment",
          "path": "Condition.stage.assessment"
        }
      ]
    },
    {
      "name": "evidence",
      "path": "Condition.evidence",
      "children": [
        {
          "name": "code",
          "path": "Condition.evidence.code"
        },
        {
          "name": "detail",
          "path": "Condition.evidence.detail"
        }
      ]
    },
    {
      "name": "note",
      "path": "Condition.note"
    }
  ],
  "Coverage": [
    {
      "name": "identifier",
      "path": "Coverage.identifier"
    },
    {
      "name": "status",
      "path": "Coverage.status"
    },
    {
      "name": "type",
      "path": "Coverage.type"
    },
    {
      "name": "policyHolder",
      "path": "Coverage.policyHolder"
    },
    {
      "name": "subscriber",
      "path": "Coverage.subscriber"
    },
    {
      "name": "subscriberId",
      "path": "Coverage.subscriberId"
    },
    {
      "name": "beneficiary",
      "path": "Coverage.beneficiary"
    },
    {
      "name": "relationship",
      "path": "Coverage.relationship"
    },
    {
      "name": "period",
      "path": "Coverage.period"
    },
    {
      "name": "payor",
      "path": "Coverage.payor"
    },
    {
      "name": "grouping",
      "path": "Coverage.grouping",
      "children": [
        {
          "name": "group",
          "path": "Coverage.grouping.group"
        },
        {
          "name": "groupDisplay",
          "path": "Coverage.grouping.groupDisplay"
        },
        {
          "name": "subGroup",
          "path": "Coverage.grouping.subGroup"
        },
        {
          "name": "subGroupDisplay",
          "path": "Coverage.grouping.subGroupDisplay"
        },
        {
          "name": "plan",
          "path": "Coverage.grouping.plan"
        },
        {
          "name": "planDisplay",
          "path": "Coverage.grouping.planDisplay"
        },
        {
          "name": "subPlan",
          "path": "Coverage.grouping.subPlan"
        },
        {
          "name": "subPlanDisplay",
          "path": "Coverage.grouping.subPlanDisplay"
        },
        {
          "name": "class",
          "path": "Coverage.grouping.class"
        },
        {
          "name": "classDisplay",
          "path": "Coverage.grouping.classDisplay"
        },
        {
          "name": "subClass",
          "path": "Coverage.grouping.subClass"
        },
        {
          "name": "subClassDisplay",
          "path": "Coverage.grouping.subClassDisplay"
        }
      ]
    },
    {
      "name": "dependent",
      "path": "Coverage.dependent"
    },
    {
      "name": "sequence",
      "path": "Coverage.sequence"
    },
    {
      "name": "order",
      "path": "Coverage.order"
    },
    {
      "name": "network",
      "path": "Coverage.network"
    },
    {
      "name": "contract",
      "path": "Coverage.contract"
    }
  ],
  "DiagnosticReport": [
    {
      "name": "identifier",
      "path": "DiagnosticReport.identifier"
    },
    {
      "name": "basedOn",
      "path": "DiagnosticReport.basedOn"
    },
    {
      "name": "status",
      "path": "DiagnosticReport.status"
    },
    {
      "name": "category",
      "path": "DiagnosticReport.category"
    },
    {
      "name": "code",
      "path": "DiagnosticReport.code"
    },
    {
      "name": "subject",
      "path": "DiagnosticReport.subject"
    },
    {
      "name": "context",
      "path": "DiagnosticReport.context"
    },
    {
      "name": "effectiveDateTime",
      "path": "DiagnosticReport.effectiveDateTime"
    },
    {
      "name": "effectivePeriod",
      "path": "DiagnosticReport.effectivePeriod"
    },
    {
      "name": "issued",
      "path": "DiagnosticReport.issued"
    },
    {
      "name": "performer",
      "path": "DiagnosticReport.performer",
      "children": [
        {
          "name": "role",
          "path": "DiagnosticReport.performer.role"
        },
        {
          "name": "actor",
          "path": "DiagnosticReport.performer.actor"
        }
      ]
    },
    {
      "name": "specimen",
      "path": "DiagnosticReport.specimen"
    },
    {
      "name": "result",
      "path": "DiagnosticReport.result"
    },
    {
      "name": "imagingStudy",
      "path": "DiagnosticReport.imagingStudy"
    },
    {
      "name": "image",
      "path": "DiagnosticReport.image",
      "children": [
        {
          "name": "comment",
          "path": "DiagnosticReport.image.comment"
        },
        {
          "name": "link",
          "path": "DiagnosticReport.image.link"
        }
      ]
    },
    {
      "name": "conclusion",
      "path": "DiagnosticReport.conclusion"
    },
    {
      "name": "codedDiagnosis",
      "path": "DiagnosticReport.codedDiagnosis"
    },
    {
      "name": "presentedForm",
      "path": "DiagnosticReport.presentedForm"
    }
  ],
  "Encounter": [
    {
      "name": "identifier",
      "path": "Encounter.identifier"
    },
    {
      "name": "status",
      "path": "Encounter.status"
    },
    {
      "name": "statusHistory",
      "path": "Encounter.statusHistory",
      "children": [
        {
          "name": "status",
          "path": "Encounter.statusHistory.status"
        },
        {
          "name": "period",
          "path": "Encounter.statusHistory.period"
        }
      ]
    },
    {
      "name": "class",
      "path": "Encounter.class"
    },
    {
      "name": "classHistory",
      "path": "Encounter.classHistory",
      "children": [
        {
          "name": "class",
          "path": "Encounter.classHistory.class"
        },
        {
          "name": "period",
          "path": "Encounter.classHistory.period"
        }
      ]
    },
    {
      "name": "type",
      "path": "Encounter.type"
    },
    {
      "name": "priority",
      "path": "Encounter.priority"
    },
    {
      "name": "subject",
      "path": "Encounter.subject"
    },
    {
      "name": "episodeOfCare",
      "path": "Encounter.episodeOfCare"
    },
    {
      "name": "incomingReferral",
      "path": "Encounter.incomingReferral"
    },
    {
      "name": "participant",
      "path": "Encounter.participant",
      "children": [
        {
          "name": "type",
          "path": "Encounter.participant.type"
        },
        {
          "name": "period",
          "path": "Encounter.participant.period"
        },
        {
          "name": "individual",
          "path": "Encounter.participant.individual"
        }
      ]
    },
    {
      "name": "appointment",
      "path": "Encounter.appointment"
    },
    {
      "name": "period",
      "path": "Encounter.period"
    },
    {
      "name": "length",
      "path": "Encounter.length"
    },
    {
      "name": "reason",
      "path": "Encounter.reason"
    },
    {
      "name": "diagnosis",
      "path": "Encounter.diagnosis",
      "children": [
        {
          "name": "condition",
          "path": "Encounter.diagnosis.condition"
        },
        {
          "name": "role",
          "path": "Encounter.diagnosis.role"
        },
        {
          "name": "rank",
          "path": "Encounter.diagnosis.rank"
        }
      ]
    },
    {
      "name": "account",
      "path": "Encounter.account"
    },
    {
      "name": "hospitalization",
      "path": "Encounter.hospitalization",
      "children": [
        {
          "name": "preAdmissionIdentifier",
          "path": "Encounter.hospitalization.preAdmissionIdentifier"
        },
        {
          "name": "origin",
          "path": "Encounter.hospitalization.origin"
        },
        {
          "name": "admitSource",
          "path": "Encounter.hospitalization.admitSource"
        },
        {
          "name": "reAdmission",
          "path": "Encounter.hospitalization.reAdmission"
        },
        {
          "name": "dietPreference",
          "path": "Encounter.hospitalization.dietPreference"
        },
        {
          "name": "specialCourtesy",
          "path": "Encounter.hospitalization.specialCourtesy"
        },
        {
          "name": "specialArrangement",
          "path": "Encounter.hospitalization.specialArrangement"
        },
        {
          "name": "destination",
          "path": "Encounter.hospitalization.destination"
        },
        {
          "name": "dischargeDisposition",
          "path": "Encounter.hospitalization.dischargeDisposition"
        }
      ]
    },
    {
      "name": "location",
      "path": "Encounter.location",
      "children": [
        {
          "name": "location",
          "path": "Encounter.location.location"
        },
        {
          "name": "status",
          "path": "Encounter.location.status"
        },
        {
          "name": "period",
          "path": "Encounter.location.period"
        }
      ]
    },
    {
      "name": "serviceProvider",
      "path": "Encounter.serviceProvider"
    },
    {
      "name": "partOf",
      "path": "Encounter.partOf"
    }
  ],
  "ExplanationOfBenefit": [
    {
      "name": "identifier",
      "path": "ExplanationOfBenefit.identifier"
    },
    {
      "name": "status",
      "path": "ExplanationOfBenefit.status"
    },
    {
      "name": "type",
      "path": "ExplanationOfBenefit.type"
    },
    {
      "name": "subType",
      "path": "ExplanationOfBenefit.subType"
    },
    {
      "name": "patient",
      "path": "ExplanationOfBenefit.patient"
    },
    {
      "name": "billablePeriod",
      "path": "ExplanationOfBenefit.billablePeriod"
    },
    {
      "name": "created",
      "path": "ExplanationOfBenefit.created"
    },
    {
      "name": "enterer",
      "path": "ExplanationOfBenefit.enterer"
    },
    {
      "name": "insurer",
      "path": "ExplanationOfBenefit.insurer"
    },
    {
      "name": "provider",
      "path": "ExplanationOfBenefit.provider"
    },
    {
      "name": "organization",
      "path": "ExplanationOfBenefit.organization"
    },
    {
      "name": "referral",
      "path": "ExplanationOfBenefit.referral"
    },
    {
      "name": "facility",
      "path": "ExplanationOfBenefit.facility"
    },
    {
      "name": "claim",
      "path": "ExplanationOfBenefit.claim"
    },
    {
      "name": "claimResponse",
      "path": "ExplanationOfBenefit.claimResponse"
    },
    {
      "name": "outcome",
      "path": "ExplanationOfBenefit.outcome"
    },
    {
      "name": "disposition",
      "path": "ExplanationOfBenefit.disposition"
    },
    {
      "name": "related",
      "path": "ExplanationOfBenefit.related",
      "children": [
        {
          "name": "claim",
          "path": "ExplanationOfBenefit.related.claim"
        },
        {
          "name": "relationship",
          "path": "ExplanationOfBenefit.related.relationship"
        },
        {
          "name": "reference",
          "path": "ExplanationOfBenefit.related.reference"
        }
      ]
    },
    {
      "name": "prescription",
      "path": "ExplanationOfBenefit.prescription"
    },
    {
      "name": "originalPrescription",
      "path": "ExplanationOfBenefit.originalPrescription"
    },
    {
      "name": "payee",
      "path": "ExplanationOfBenefit.payee",
      "children": [
        {
          "name": "type",
          "path": "ExplanationOfBenefit.payee.type"
        },
        {
          "name": "resourceType",
          "path": "ExplanationOfBenefit.payee.resourceType"
        },
        {
          "name": "party",
          "path": "ExplanationOfBenefit.payee.party"
        }
      ]
    },
    {
      "name": "information",
      "path": "ExplanationOfBenefit.information",
      "children": [
        {
          "name": "sequence",
          "path": "ExplanationOfBenefit.information.sequence"
        },
        {
          "name": "category",
          "path": "ExplanationOfBenefit.information.category"
        },
        {
          "name": "code",
          "path": "ExplanationOfBenefit.information.code"
        },
        {
          "name": "timingDate",
          "path": "ExplanationOfBenefit.information.timingDate"
        },
        {
          "name": "timingPeriod",
          "path": "ExplanationOfBenefit.information.timingPeriod"
        },
        {
          "name": "valueString",
          "path": "ExplanationOfBenefit.information.valueString"
        },
        {
          "name": "valueQuantity",
          "path": "ExplanationOfBenefit.information.valueQuantity"
        },
        {
          "name": "valueAttachment",
          "path": "ExplanationOfBenefit.information.valueAttachment"
        },
        {
          "name": "valueReference",
          "path": "ExplanationOfBenefit.information.valueReference"
        },
        {
          "name": "reason",
          "path": "ExplanationOfBenefit.information.reason"
        }
      ]
    },
    {
      "name": "careTeam",
      "path": "ExplanationOfBenefit.careTeam",
      "children": [
        {
          "name": "sequence",
          "path": "ExplanationOfBenefit.careTeam.sequence"
        },
        {
          "name": "provider",
          "path": "ExplanationOfBenefit.careTeam.provider"
        },
        {
          "name": "responsible",
          "path": "ExplanationOfBenefit.careTeam.responsible"
        },
        {
          "name": "role",
          "path": "ExplanationOfBenefit.careTeam.role"
        },
        {
          "name": "qualification",
          "path": "ExplanationOfBenefit.careTeam.qualification"
        }
      ]
    },
    {
      "name": "diagnosis",
      "path": "ExplanationOfBenefit.diagnosis",
      "children": [
        {
          "name": "sequence",
          "path": "ExplanationOfBenefit.diagnosis.sequence"
        },
        {
          "name": "diagnosisCodeableConcept",
          "path": "ExplanationOfBenefit.diagnosis.diagnosisCodeableConcept"
        },
        {
          "name": "diagnosisReference",
          "path": "ExplanationOfBenefit.diagnosis.diagnosisReference"
        },
        {
          "name": "type",
          "path": "ExplanationOfBenefit.diagnosis.type"
        },
        {
          "name": "packageCode",
          "path": "ExplanationOfBenefit.diagnosis.packageCode"
        }
      ]
    },
    {
      "name": "procedure",
      "path": "ExplanationOfBenefit.procedure",
      "children": [
        {
          "name": "sequence",
          "path": "ExplanationOfBenefit.procedure.sequence"
        },
        {
          "name": "date",
          "path": "ExplanationOfBenefit.procedure.date"
        },
        {
          "name": "procedureCodeableConcept",
          "path": "ExplanationOfBenefit.procedure.procedureCodeableConcept"
        },
        {
          "name": "procedureReference",
          "path": "ExplanationOfBenefit.procedure.procedureReference"
        }
      ]
    },
    {
      "name": "precedence",
      "path": "ExplanationOfBenefit.precedence"
    },
    {
      "name": "insurance",
      "path": "ExplanationOfBenefit.insurance",
      "children": [
        {
          "name": "coverage",
          "path": "ExplanationOfBenefit.insurance.coverage"
        },
        {
          "name": "preAuthRef",
          "path": "ExplanationOfBenefit.insurance.preAuthRef"
        }
      ]
    },
    {
      "name": "accident",
      "path": "ExplanationOfBenefit.accident",
      "children": [
        {
          "name": "date",
          "path": "ExplanationOfBenefit.accident.date"
        },
        {
          "name": "type",
          "path": "ExplanationOfBenefit.accident.type"
        },
        {
          "name": "locationAddress",
          "path": "ExplanationOfBenefit.accident.locationAddress"
        },
        {
          "name": "locationReference",
          "path": "ExplanationOfBenefit.accident.locationReference"
        }
      ]
    },
    {
      "name": "employmentImpacted",
      "path": "ExplanationOfBenefit.employmentImpacted"
    },
    {
      "name": "hospitalization",
      "path": "ExplanationOfBenefit.hospitalization"
    },
    {
      "name": "item",
      "path": "ExplanationOfBenefit.item",
      "children": [
        {
          "name": "sequence",
          "path": "ExplanationOfBenefit.item.sequence"
        },
        {
          "name": "careTeamLinkId",
          "path": "ExplanationOfBenefit.item.careTeamLinkId"
        },
        {
          "name": "diagnosisLinkId",
          "path": "ExplanationOfBenefit.item.diagnosisLinkId"
        },
        {
          "name": "procedureLinkId",
          "path": "ExplanationOfBenefit.item.procedureLinkId"
        },
        {
          "name": "informationLinkId",
          "path": "ExplanationOfBenefit.item.informationLinkId"
        },
        {
          "name": "revenue",
          "path": "ExplanationOfBenefit.item.revenue"
        },
        {
          "name": "category",
          "path": "ExplanationOfBenefit.item.category"
        },
        {
          "name": "service",
          "path": "ExplanationOfBenefit.item.service"
        },
        {
          "name": "modifier",
          "path": "ExplanationOfBenefit.item.modifier"
        },
        {
          "name": "programCode",
          "path": "ExplanationOfBenefit.item.programCode"
        },
        {
          "name": "servicedDate",
          "path": "ExplanationOfBenefit.item.servicedDate"
        },
        {
          "name": "servicedPeriod",
          "path": "ExplanationOfBenefit.item.servicedPeriod"
        },
        {
          "name": "locationCodeableConcept",
          "path": "ExplanationOfBenefit.item.locationCodeableConcept"
        },
        {
          "name": "locationAddress",
          "path": "ExplanationOfBenefit.item.locationAddress"
        },
        {
          "name": "locationReference",
          "path": "ExplanationOfBenefit.item.locationReference"
        },
        {
          "name": "quantity",
          "path": "ExplanationOfBenefit.item.quantity"
        },
        {
          "name": "unitPrice",
          "path": "ExplanationOfBenefit.item.unitPrice"
        },
        {
          "name": "factor",
          "path": "ExplanationOfBenefit.item.factor"
        },
        {
          "name": "net",
          "path": "ExplanationOfBenefit.item.net"
        },
        {
          "name": "udi",
          "path": "ExplanationOfBenefit.item.udi"
        },
        {
          "name": "bodySite",
          "path": "ExplanationOfBenefit.item.bodySite"
        },
        {
          "name": "subSite",
          "path": "ExplanationOfBenefit.item.subSite"
        },
        {
          "name": "encounter",
          "path": "ExplanationOfBenefit.item.encounter"
        },
        {
          "name": "noteNumber",
          "path": "ExplanationOfBenefit.item.noteNumber"
        },
        {
          "name": "adjudication",
          "path": "ExplanationOfBenefit.item.adjudication",
          "children": [
            {
              "name": "category",
              "path": "ExplanationOfBenefit.item.adjudication.category"
            },
            {
              "name": "reason",
              "path": "ExplanationOfBenefit.item.adjudication.reason"
            },
            {
              "name": "amount",
              "path": "ExplanationOfBenefit.item.adjudication.amount"
            },
            {
              "name": "value",
              "path": "ExplanationOfBenefit.item.adjudication.value"
            }
          ]
        },
        {
          "name": "detail",
          "path": "ExplanationOfBenefit.item.detail",
          "children": [
            {
              "name": "sequence",
              "path": "ExplanationOfBenefit.item.detail.sequence"
            },
            {
              "name": "type",
              "path": "ExplanationOfBenefit.item.detail.type"
            },
            {
              "name": "revenue",
              "path": "ExplanationOfBenefit.item.detail.revenue"
            },
            {
              "name": "category",
              "path": "ExplanationOfBenefit.item.detail.category"
            },
            {
              "name": "service",
              "path": "ExplanationOfBenefit.item.detail.service"
            },
            {
              "name": "modifier",
              "path": "ExplanationOfBenefit.item.detail.modifier"
            },
            {
              "name": "programCode",
              "path": "ExplanationOfBenefit.item.detail.programCode"
            },
            {
              "name": "quantity",
              "path": "ExplanationOfBenefit.item.detail.quantity"
            },
            {
              "name": "unitPrice",
              "path": "ExplanationOfBenefit.item.detail.unitPrice"
            },
            {
              "name": "factor",
              "path": "ExplanationOfBenefit.item.detail.factor"
            },
            {
              "name": "net",
              "path": "ExplanationOfBenefit.item.detail.net"
            },
            {
              "name": "udi",
              "path": "ExplanationOfBenefit.item.detail.udi"
            },
            {
              "name": "noteNumber",
              "path": "ExplanationOfBenefit.item.detail.noteNumber"
            },
            {
              "name": "adjudication",
              "path": "ExplanationOfBenefit.item.detail.adjudication"
            },
            {
              "name": "subDetail",
              "path": "ExplanationOfBenefit.item.detail.subDetail",
              "children": [
                {
                  "name": "sequence",
                  "path": "ExplanationOfBenefit.item.detail.subDetail.sequence"
                },
                {
                  "name": "type",
                  "path": "ExplanationOfBenefit.item.detail.subDetail.type"
                },
                {
                  "name": "revenue",
                  "path": "ExplanationOfBenefit.item.detail.subDetail.revenue"
                },
                {
                  "name": "category",
                  "path": "ExplanationOfBenefit.item.detail.subDetail.category"
                },
                {
                  "name": "service",
                  "path": "ExplanationOfBenefit.item.detail.subDetail.service"
                },
                {
                  "name": "modifier",
                  "path": "ExplanationOfBenefit.item.detail.subDetail.modifier"
                },
                {
                  "name": "programCode",
                  "path": "ExplanationOfBenefit.item.detail.subDetail.programCode"
                },
                {
                  "name": "quantity",
                  "path": "ExplanationOfBenefit.item.detail.subDetail.quantity"
                },
                {
                  "name": "unitPrice",
                  "path": "ExplanationOfBenefit.item.detail.subDetail.unitPrice"
                },
                {
                  "name": "factor",
                  "path": "ExplanationOfBenefit.item.detail.subDetail.factor"
                },
                {
                  "name": "net",
                  "path": "ExplanationOfBenefit.item.detail.subDetail.net"
                },
                {
                  "name": "udi",
                  "path": "ExplanationOfBenefit.item.detail.subDetail.udi"
                },
                {
                  "name": "noteNumber",
                  "path": "ExplanationOfBenefit.item.detail.subDetail.noteNumber"
                },
                {
                  "name": "adjudication",
                  "path": "ExplanationOfBenefit.item.detail.subDetail.adjudication"
                }
              ]
            }
          ]
        }
      ]
    },
    {
      "name": "addItem",
      "path": "ExplanationOfBenefit.addItem",
      "children": [
        {
          "name": "sequenceLinkId",
          "path": "ExplanationOfBenefit.addItem.sequenceLinkId"
        },
        {
          "name": "revenue",
          "path": "ExplanationOfBenefit.addItem.revenue"
        },
        {
          "name": "category",
          "path": "ExplanationOfBenefit.addItem.category"
        },
        {
          "name": "service",
          "path": "ExplanationOfBenefit.addItem.service"
        },
        {
          "name": "modifier",
          "path": "ExplanationOfBenefit.addItem.modifier"
        },
        {
          "name": "fee",
          "path": "ExplanationOfBenefit.addItem.fee"
        },
        {
          "name": "noteNumber",
          "path": "ExplanationOfBenefit.addItem.noteNumber"
        },
        {
          "name": "adjudication",
          "path": "ExplanationOfBenefit.addItem.adjudication"
        },
        {
          "name": "detail",
          "path": "ExplanationOfBenefit.addItem.detail",
          "children": [
            {
              "name": "revenue",
              "path": "ExplanationOfBenefit.addItem.detail.revenue"
            },
            {
              "name": "category",
              "path": "ExplanationOfBenefit.addItem.detail.category"
            },
            {
              "name": "service",
              "path": "ExplanationOfBenefit.addItem.detail.service"
            },
            {
              "name": "modifier",
              "path": "ExplanationOfBenefit.addItem.detail.modifier"
            },
            {
              "name": "fee",
              "path": "ExplanationOfBenefit.addItem.detail.fee"
            },
            {
              "name": "noteNumber",
              "path": "ExplanationOfBenefit.addItem.detail.noteNumber"
            },
            {
              "name": "adjudication",
              "path": "ExplanationOfBenefit.addItem.detail.adjudication"
            }
          ]
        }
      ]
    },
    {
      "name": "totalCost",
      "path": "ExplanationOfBenefit.totalCost"
    },
    {
      "name": "unallocDeductable",
      "path": "ExplanationOfBenefit.unallocDeductable"
    },
    {
      "name": "totalBenefit",
      "path": "ExplanationOfBenefit.totalBenefit"
    },
    {
      "name": "payment",
      "path": "ExplanationOfBenefit.payment",
      "children": [
        {
          "name": "type",
          "path": "ExplanationOfBenefit.payment.type"
        },
        {
          "name": "adjustment",
          "path": "ExplanationOfBenefit.payment.adjustment"
        },
        {
          "name": "adjustmentReason",
          "path": "ExplanationOfBenefit.payment.adjustmentReason"
        },
        {
          "name": "date",
          "path": "ExplanationOfBenefit.payment.date"
        },
        {
          "name": "amount",
          "path": "ExplanationOfBenefit.payment.amount"
        },
        {
          "name": "identifier",
          "path": "ExplanationOfBenefit.payment.identifier"
        }
      ]
    },
    {
      "name": "form",
      "path": "ExplanationOfBenefit.form"
    },
    {
      "name": "processNote",
      "path": "ExplanationOfBenefit.processNote",
      "children": [
        {
          "name": "number",
          "path": "ExplanationOfBenefit.processNote.number"
        },
        {
          "name": "type",
          "path": "ExplanationOfBenefit.processNote.type"
        },
        {
          "name": "text",
          "path": "ExplanationOfBenefit.processNote.text"
        },
        {
          "name": "language",
          "path": "ExplanationOfBenefit.processNote.language"
        }
      ]
    },
    {
      "name": "benefitBalance",
      "path": "ExplanationOfBenefit.benefitBalance",
      "children": [
        {
          "name": "category",
          "path": "ExplanationOfBenefit.benefitBalance.category"
        },
        {
          "name": "subCategory",
          "path": "ExplanationOfBenefit.benefitBalance.subCategory"
        },
        {
          "name": "excluded",
          "path": "ExplanationOfBenefit.benefitBalance.excluded"
        },
        {
          "name": "name",
          "path": "ExplanationOfBenefit.benefitBalance.name"
        },
        {
          "name": "description",
          "path": "ExplanationOfBenefit.benefitBalance.description"
        },
        {
          "name": "network",
          "path": "ExplanationOfBenefit.benefitBalance.network"
        },
        {
          "name": "unit",
          "path": "ExplanationOfBenefit.benefitBalance.unit"
        },
        {
          "name": "term",
          "path": "ExplanationOfBenefit.benefitBalance.term"
        },
        {
          "name": "financial",
          "path": "ExplanationOfBenefit.benefitBalance.financial",
          "children": [
            {
              "name": "type",
              "path": "ExplanationOfBenefit.benefitBalance.financial.type"
            },
            {
              "name": "allowedUnsignedInt",
              "path": "ExplanationOfBenefit.benefitBalance.financial.allowedUnsignedInt"
            },
            {
              "name": "allowedString",
              "path": "ExplanationOfBenefit.benefitBalance.financial.allowedString"
            },
            {
              "name": "allowedMoney",
              "path": "ExplanationOfBenefit.benefitBalance.financial.allowedMoney"
            },
            {
              "name": "usedUnsignedInt",
              "path": "ExplanationOfBenefit.benefitBalance.financial.usedUnsignedInt"
            },
            {
              "name": "usedMoney",
              "path": "ExplanationOfBenefit.benefitBalance.financial.usedMoney"
            }
          ]
        }
      ]
    }
  ],
  "ImagingStudy": [
    {
      "name": "uid",
      "path": "ImagingStudy.uid"
    },
    {
      "name": "accession",
      "path": "ImagingStudy.accession"
    },
    {
      "name": "identifier",
      "path": "ImagingStudy.identifier"
    },
    {
      "name": "availability",
      "path": "ImagingStudy.availability"
    },
    {
      "name": "modalityList",
      "path": "ImagingStudy.modalityList"
    },
    {
      "name": "patient",
      "path": "ImagingStudy.patient"
    },
    {
      "name": "context",
      "path": "ImagingStudy.context"
    },
    {
      "name": "started",
      "path": "ImagingStudy.started"
    },
    {
      "name": "basedOn",
      "path": "ImagingStudy.basedOn"
    },
    {
      "name": "referrer",
      "path": "ImagingStudy.referrer"
    },
    {
      "name": "interpreter",
      "path": "ImagingStudy.interpreter"
    },
    {
      "name": "endpoint",
      "path": "ImagingStudy.endpoint"
    },
    {
      "name": "numberOfSeries",
      "path": "ImagingStudy.numberOfSeries"
    },
    {
      "name": "numberOfInstances",
      "path": "ImagingStudy.numberOfInstances"
    },
    {
      "name": "procedureReference",
      "path": "ImagingStudy.procedureReference"
    },
    {
      "name": "procedureCode",
      "path": "ImagingStudy.procedureCode"
    },
    {
      "name": "reason",
      "path": "ImagingStudy.reason"
    },
    {
      "name": "description",
      "path": "ImagingStudy.description"
    },
    {
      "name": "series",
      "path": "ImagingStudy.series",
      "children": [
        {
          "name": "uid",
          "path": "ImagingStudy.series.uid"
        },
        {
          "name": "number",
          "path": "ImagingStudy.series.number"
        },
        {
          "name": "modality",
          "path": "ImagingStudy.series.modality"
        },
        {
          "name": "description",
          "path": "ImagingStudy.series.description"
        },
        {
          "name": "numberOfInstances",
          "path": "ImagingStudy.series.numberOfInstances"
        },
        {
          "name": "availability",
          "path": "ImagingStudy.series.availability"
        },
        {
          "name": "endpoint",
          "path": "ImagingStudy.series.endpoint"
        },
        {
          "name": "bodySite",
          "path": "ImagingStudy.series.bodySite"
        },
        {
          "name": "laterality",
          "path": "ImagingStudy.series.laterality"
        },
        {
          "name": "started",
          "path": "ImagingStudy.series.started"
        },
        {
          "name": "performer",
          "path": "ImagingStudy.series.performer"
        },
        {
          "name": "instance",
          "path": "ImagingStudy.series.instance",
          "children": [
            {
              "name": "uid",
              "path": "ImagingStudy.series.instance.uid"
            },
            {
              "name": "number",
              "path": "ImagingStudy.series.instance.number"
            },
            {
              "name": "sopClass",
              "path": "ImagingStudy.series.instance.sopClass"
            },
            {
              "name": "title",
              "path": "ImagingStudy.series.instance.title"
            }
          ]
        }
      ]
    }
  ],
  "Immunization": [
    {
      "name": "identifier",
      "path": "Immunization.identifier"
    },
    {
      "name": "status",
      "path": "Immunization.status"
    },
    {
      "name": "notGiven",
      "path": "Immunization.notGiven"
    },
    {
      "name": "vaccineCode",
      "path": "Immunization.vaccineCode"
    },
    {
      "name": "patient",
      "path": "Immunization.patient"
    },
    {
      "name": "encounter",
      "path": "Immunization.encounter"
    },
    {
      "name": "date",
      "path": "Immunization.date"
    },
    {
      "name": "primarySource",
      "path": "Immunization.primarySource"
    },
    {
      "name": "reportOrigin",
      "path": "Immunization.reportOrigin"
    },
    {
      "name": "location",
      "path": "Immunization.location"
    },
    {
      "name": "manufacturer",
      "path": "Immunization.manufacturer"
    },
    {
      "name": "lotNumber",
      "path": "Immunization.lotNumber"
    },
    {
      "name": "expirationDate",
      "path": "Immunization.expirationDate"
    },
    {
      "name": "site",
      "path": "Immunization.site"
    },
    {
      "name": "route",
      "path": "Immunization.route"
    },
    {
      "name": "doseQuantity",
      "path": "Immunization.doseQuantity"
    },
    {
      "name": "practitioner",
      "path": "Immunization.practitioner",
      "children": [
        {
          "name": "role",
          "path": "Immunization.practitioner.role"
        },
        {
          "name": "actor",
          "path": "Immunization.practitioner.actor"
        }
      ]
    },
    {
      "name": "note",
      "path": "Immunization.note"
    },
    {
      "name": "explanation",
      "path": "Immunization.explanation",
      "children": [
        {
          "name": "reason",
          "path": "Immunization.explanation.reason"
        },
        {
          "name": "reasonNotGiven",
          "path": "Immunization.explanation.reasonNotGiven"
        }
      ]
    },
    {
      "name": "reaction",
      "path": "Immunization.reaction",
      "children": [
        {
          "name": "date",
          "path": "Immunization.reaction.date"
        },
        {
          "name": "detail",
          "path": "Immunization.reaction.detail"
        },
        {
          "name": "reported",
          "path": "Immunization.reaction.reported"
        }
      ]
    },
    {
      "name": "vaccinationProtocol",
      "path": "Immunization.vaccinationProtocol",
      "children": [
        {
          "name": "doseSequence",
          "path": "Immunization.vaccinationProtocol.doseSequence"
        },
        {
          "name": "description",
          "path": "Immunization.vaccinationProtocol.description"
        },
        {
          "name": "authority",
          "path": "Immunization.vaccinationProtocol.authority"
        },
        {
          "name": "series",
          "path": "Immunization.vaccinationProtocol.series"
        },
        {
          "name": "seriesDoses",
          "path": "Immunization.vaccinationProtocol.seriesDoses"
        },
        {
          "name": "targetDisease",
          "path": "Immunization.vaccinationProtocol.targetDisease"
        },
        {
          "name": "doseStatus",
          "path": "Immunization.vaccinationProtocol.doseStatus"
        },
        {
          "name": "doseStatusReason",
          "path": "Immunization.vaccinationProtocol.doseStatusReason"
        }
      ]
    }
  ],
  "MedicationRequest": [
    {
      "name": "identifier",
      "path": "MedicationRequest.identifier"
    },
    {
      "name": "definition",
      "path": "MedicationRequest.definition"
    },
    {
      "name": "basedOn",
      "path": "MedicationRequest.basedOn"
    },
    {
      "name": "groupIdentifier",
      "path": "MedicationRequest.groupIdentifier"
    },
    {
      "name": "status",
      "path": "MedicationRequest.status"
    },
    {
      "name": "intent",
      "path": "MedicationRequest.intent"
    },
    {
      "name": "category",
      "path": "MedicationRequest.category"
    },
    {
      "name": "priority",
      "path": "MedicationRequest.priority"
    },
    {
      "name": "medicationCodeableConcept",
      "path": "MedicationRequest.medicationCodeableConcept"
    },
    {
      "name": "medicationReference",
      "path": "MedicationRequest.medicationReference"
    },
    {
      "name": "subject",
      "path": "MedicationRequest.subject"
    },
    {
      "name": "context",
      "path": "MedicationRequest.context"
    },
    {
      "name": "supportingInformation",
      "path": "MedicationRequest.supportingInformation"
    },
    {
      "name": "authoredOn",
      "path": "MedicationRequest.authoredOn"
    },
    {
      "name": "requester",
      "path": "MedicationRequest.requester",
      "children": [
        {
          "name": "agent",
          "path": "MedicationRequest.requester.agent"
        },
        {
          "name": "onBehalfOf",
          "path": "MedicationRequest.requester.onBehalfOf"
        }
      ]
    },
    {
      "name": "recorder",
      "path": "MedicationRequest.recorder"
    },
    {
      "name": "reasonCode",
      "path": "MedicationRequest.reasonCode"
    },
    {
      "name": "reasonReference",
      "path": "MedicationRequest.reasonReference"
    },
    {
      "name": "note",
      "path": "MedicationRequest.note"
    },
    {
      "name": "dosageInstruction",
      "path": "MedicationRequest.dosageInstruction"
    },
    {
      "name": "dispenseRequest",
      "path": "MedicationRequest.dispenseRequest",
      "children": [
        {
          "name": "validityPeriod",
          "path": "MedicationRequest.dispenseRequest.validityPeriod"
        },
        {
          "name": "numberOfRepeatsAllowed",
          "path": "MedicationRequest.dispenseRequest.numberOfRepeatsAllowed"
        },
        {
          "name": "quantity",
          "path": "MedicationRequest.dispenseRequest.quantity"
        },
        {
          "name": "expectedSupplyDuration",
          "path": "MedicationRequest.dispenseRequest.expectedSupplyDuration"
        },
        {
          "name": "performer",
          "path": "MedicationRequest.dispenseRequest.performer"
        }
      ]
    },
    {
      "name": "substitution",
      "path": "MedicationRequest.substitution",
      "children": [
        {
          "name": "allowed",
          "path": "MedicationRequest.substitution.allowed"
        },
        {
          "name": "reason",
          "path": "MedicationRequest.substitution.reason"
        }
      ]
    },
    {
      "name": "priorPrescription",
      "path": "MedicationRequest.priorPrescription"
    },
    {
      "name": "detectedIssue",
      "path": "MedicationRequest.detectedIssue"
    },
    {
      "name": "eventHistory",
      "path": "MedicationRequest.eventHistory"
    }
  ],
  "Observation": [
    {
      "name": "identifier",
      "path": "Observation.identifier"
    },
    {
      "name": "basedOn",
      "path": "Observation.basedOn"
    },
    {
      "name": "status",
      "path": "Observation.status"
    },
    {
      "name": "category",
      "path": "Observation.category"
    },
    {
      "name": "code",
      "path": "Observation.code"
    },
    {
      "name": "subject",
      "path": "Observation.subject"
    },
    {
      "name": "context",
      "path": "Observation.context"
    },
    {
      "name": "effectiveDateTime",
      "path": "Observation.effectiveDateTime"
    },
    {
      "name": "effectivePeriod",
      "path": "Observation.effectivePeriod"
    },
    {
      "name": "issued",
      "path": "Observation.issued"
    },
    {
      "name": "performer",
      "path": "Observation.performer"
    },
    {
      "name": "valueQuantity",
      "path": "Observation.valueQuantity"
    },
    {
      "name": "valueCodeableConcept",
      "path": "Observation.valueCodeableConcept"
    },
    {
      "name": "valueString",
      "path": "Observation.valueString"
    },
    {
      "name": "valueBoolean",
      "path": "Observation.valueBoolean"
    },
    {
      "name": "valueRange",
      "path": "Observation.valueRange"
    },
    {
      "name": "valueRatio",
      "path": "Observation.valueRatio"
    },
    {
      "name": "valueSampledData",
      "path": "Observation.valueSampledData"
    },
    {
      "name": "valueAttachment",
      "path": "Observation.valueAttachment"
    },
    {
      "name": "valueTime",
      "path": "Observation.valueTime"
    },
    {
      "name": "valueDateTime",
      "path": "Observation.valueDateTime"
    },
    {
      "name": "valuePeriod",
      "path": "Observation.valuePeriod"
    },
    {
      "name": "dataAbsentReason",
      "path": "Observation.dataAbsentReason"
    },
    {
      "name": "interpretation",
      "path": "Observation.interpretation"
    },
    {
      "name": "comment",
      "path": "Observation.comment"
    },
    {
      "name": "bodySite",
      "path": "Observation.bodySite"
    },
    {
      "name": "method",
      "path": "Observation.method"
    },
    {
      "name": "specimen",
      "path": "Observation.specimen"
    },
    {
      "name": "device",
      "path": "Observation.device"
    },
    {
      "name": "referenceRange",
      "path": "Observation.referenceRange",
      "children": [
        {
          "name": "low",
          "path": "Observation.referenceRange.low"
        },
        {
          "name": "high",
          "path": "Observation.referenceRange.high"
        },
        {
          "name": "type",
          "path": "Observation.referenceRange.type"
        },
        {
          "name": "appliesTo",
          "path": "Observation.referenceRange.appliesTo"
        },
        {
          "name": "age",
          "path": "Observation.referenceRange.age"
        },
        {
          "name": "text",
          "path": "Observation.referenceRange.text"
        }
      ]
    },
    {
      "name": "related",
      "path": "Observation.related",
      "children": [
        {
          "name": "type",
          "path": "Observation.related.type"
        },
        {
          "name": "target",
          "path": "Observation.related.target"
        }
      ]
    },
    {
      "name": "component",
      "path": "Observation.component",
      "children": [
        {
          "name": "code",
          "path": "Observation.component.code"
        },
        {
          "name": "valueQuantity",
          "path": "Observation.component.valueQuantity"
        },
        {
          "name": "valueCodeableConcept",
          "path": "Observation.component.valueCodeableConcept"
        },
        {
          "name": "valueString",
          "path": "Observation.component.valueString"
        },
        {
          "name": "valueRange",
          "path": "Observation.component.valueRange"
        },
        {
          "name": "valueRatio",
          "path": "Observation.component.valueRatio"
        },
        {
          "name": "valueSampledData",
          "path": "Observation.component.valueSampledData"
        },
        {
          "name": "valueAttachment",
          "path": "Observation.component.valueAttachment"
        },
        {
          "name": "valueTime",
          "path": "Observation.component.valueTime"
        },
        {
          "name": "valueDateTime",
          "path": "Observation.component.valueDateTime"
        },
        {
          "name": "valuePeriod",
          "path": "Observation.component.valuePeriod"
        },
        {
          "name": "dataAbsentReason",
          "path": "Observation.component.dataAbsentReason"
        },
        {
          "name": "interpretation",
          "path": "Observation.component.interpretation"
        },
        {
          "name": "referenceRange",
          "path": "Observation.component.referenceRange"
        }
      ]
    }
  ],
  "Patient": [
    {
      "name": "identifier",
      "path": "Patient.identifier"
    },
    {
      "name": "active",
      "path": "Patient.active"
    },
    {
      "name": "name",
      "path": "Patient.name"
    },
    {
      "name": "telecom",
      "path": "Patient.telecom"
    },
    {
      "name": "gender",
      "path": "Patient.gender"
    },
    {
      "name": "birthDate",
      "path": "Patient.birthDate"
    },
    {
      "name": "deceasedBoolean",
      "path": "Patient.deceasedBoolean"
    },
    {
      "name": "deceasedDateTime",
      "path": "Patient.deceasedDateTime"
    },
    {
      "name": "address",
      "path": "Patient.address"
    },
    {
      "name": "maritalStatus",
      "path": "Patient.maritalStatus"
    },
    {
      "name": "multipleBirthBoolean",
      "path": "Patient.multipleBirthBoolean"
    },
    {
      "name": "multipleBirthInteger",
      "path": "Patient.multipleBirthInteger"
    },
    {
      "name": "photo",
      "path": "Patient.photo"
    },
    {
      "name": "contact",
      "path": "Patient.contact",
      "children": [
        {
          "name": "relationship",
          "path": "Patient.contact.relationship"
        },
        {
          "name": "name",
          "path": "Patient.contact.name"
        },
        {
          "name": "telecom",
          "path": "Patient.contact.telecom"
        },
        {
          "name": "address",
          "path": "Patient.contact.address"
        },
        {
          "name": "gender",
          "path": "Patient.contact.gender"
        },
        {
          "name": "organization",
          "path": "Patient.contact.organization"
        },
        {
          "name": "period",
          "path": "Patient.contact.period"
        }
      ]
    },
    {
      "name": "animal",
      "path": "Patient.animal",
      "children": [
        {
          "name": "species",
          "path": "Patient.animal.species"
        },
        {
          "name": "breed",
          "path": "Patient.animal.breed"
        },
        {
          "name": "genderStatus",
          "path": "Patient.animal.genderStatus"
        }
      ]
    },
    {
      "name": "communication",
      "path": "Patient.communication",
      "children": [
        {
          "name": "language",
          "path": "Patient.communication.language"
        },
        {
          "name": "preferred",
          "path": "Patient.communication.preferred"
        }
      ]
    },
    {
      "name": "generalPractitioner",
      "path": "Patient.generalPractitioner"
    },
    {
      "name": "managingOrganization",
      "path": "Patient.managingOrganization"
    },
    {
      "name": "link",
      "path": "Patient.link",
      "children": [
        {
          "name": "other",
          "path": "Patient.link.other"
        },
        {
          "name": "type",
          "path": "Patient.link.type"
        }
      ]
    }
  ],
  "ProcedureRequest": [
    {
      "name": "identifier",
      "path": "ProcedureRequest.identifier"
    },
    {
      "name": "definition",
      "path": "ProcedureRequest.definition"
    },
    {
      "name": "basedOn",
      "path": "ProcedureRequest.basedOn"
    },
    {
      "name": "replaces",
      "path": "ProcedureRequest.replaces"
    },
    {
      "name": "requisition",
      "path": "ProcedureRequest.requisition"
    },
    {
      "name": "status",
      "path": "ProcedureRequest.status"
    },
    {
      "name": "intent",
      "path": "ProcedureRequest.intent"
    },
    {
      "name": "priority",
      "path": "ProcedureRequest.priority"
    },
    {
      "name": "doNotPerform",
      "path": "ProcedureRequest.doNotPerform"
    },
    {
      "name": "category",
      "path": "ProcedureRequest.category"
    },
    {
      "name": "code",
      "path": "ProcedureRequest.code"
    },
    {
      "name": "subject",
      "path": "ProcedureRequest.subject"
    },
    {
      "name": "context",
      "path": "ProcedureRequest.context"
    },
    {
      "name": "occurrenceDateTime",
      "path": "ProcedureRequest.occurrenceDateTime"
    },
    {
      "name": "occurrencePeriod",
      "path": "ProcedureRequest.occurrencePeriod"
    },
    {
      "name": "occurrenceTiming",
      "path": "ProcedureRequest.occurrenceTiming"
    },
    {
      "name": "asNeededBoolean",
      "path": "ProcedureRequest.asNeededBoolean"
    },
    {
      "name": "asNeededCodeableConcept",
      "path": "ProcedureRequest.asNeededCodeableConcept"
    },
    {
      "name": "authoredOn",
      "path": "ProcedureRequest.authoredOn"
    },
    {
      "name": "requester",
      "path": "ProcedureRequest.requester",
      "children": [
        {
          "name": "agent",
          "path": "ProcedureRequest.requester.agent"
        },
        {
          "name": "onBehalfOf",
          "path": "ProcedureRequest.requester.onBehalfOf"
        }
      ]
    },
    {
      "name": "performerType",
      "path": "ProcedureRequest.performerType"
    },
    {
      "name": "performer",
      "path": "ProcedureRequest.performer"
    },
    {
      "name": "reasonCode",
      "path": "ProcedureRequest.reasonCode"
    },
    {
      "name": "reasonReference",
      "path": "ProcedureRequest.reasonReference"
    },
    {
      "name": "supportingInfo",
      "path": "ProcedureRequest.supportingInfo"
    },
    {
      "name": "specimen",
      "path": "ProcedureRequest.specimen"
    },
    {
      "name": "bodySite",
      "path": "ProcedureRequest.bodySite"
    },
    {
      "name": "note",
      "path": "ProcedureRequest.note"
    },
    {
      "name": "relevantHistory",
      "path": "ProcedureRequest.relevantHistory"
    }
  ]
}