{
  "Organization": [
    {
      "name": "assigner",
      "path": "Identifier.assigner",
      "type": "Reference",
      "definition": "Organization that issued/manages the identifier.",
      "referenceTypes": [
        "Organization"
      ]
    },
    {
      "name": "assigner",
      "path": "Identifier.assigner",
      "type": "Reference",
      "definition": "Organization that issued/manages the identifier.",
      "referenceTypes": [
        "Organization"
      ]
    },
    {
      "name": "author",
      "path": "CarePlan.author",
      "type": "Reference",
      "definition": "Identifies the individual(s) or ogranization who is responsible for the content of the care plan.",
      "referenceTypes": [
        "Patient",
        "Practitioner",
        "RelatedPerson",
        "Organization",
        "CareTeam"
      ]
    },
    {
      "name": "performer",
      "path": "CarePlan.activity.detail.performer",
      "type": "Reference",
      "definition": "Identifies who's expected to be involved in the activity.",
      "referenceTypes": [
        "Practitioner",
        "Organization",
        "RelatedPerson",
        "Patient",
        "CareTeam"
      ]
    },
    {
      "name": "assigner",
      "path": "Identifier.assigner",
      "type": "Reference",
      "definition": "Organization that issued/manages the identifier.",
      "referenceTypes": [
        "Organization"
      ]
    },
    {
      "name": "insurer",
      "path": "Claim.insurer",
      "type": "Reference",
      "definition": "The Insurer who is target of the request.",
      "referenceTypes": [
        "Organization"
      ]
    },
    {
      "name": "organization",
      "path": "Claim.organization",
      "type": "Reference",
      "definition": "The organization which is responsible for the bill, claim pre-determination, pre-authorization.",
      "referenceTypes": [
        "Organization"
      ]
    },
    {
      "name": "assigner",
      "path": "Identifier.assigner",
      "type": "Reference",
      "definition": "Organization that issued/manages the identifier.",
      "referenceTypes": [
        "Organization"
      ]
    },
    {
      "name": "party",
      "path": "Claim.payee.party",
      "type": "Reference",
      "definition": "Party to be reimbursed: Subscriber, provider, other.",
      "referenceTypes": [
        "Practitioner",
        "Organization",
        "Patient",
        "RelatedPerson"
      ]
    },
    {
      "name": "provider",
      "path": "Claim.careTeam.provider",
      "type": "Reference",
      "definition": "Member of the team who provided the overall service.",
      "referenceTypes": [
        "Practitioner",
        "Organization"
      ]
    },
    {
      "name": "assigner",
      "path": "Identifier.assigner",
      "type": "Reference",
      "definition": "Organization that issued/manages the identifier.",
      "referenceTypes": [
        "Organization"
      ]
    },
    {
      "name": "assigner",
      "path": "Identifier.assigner",
      "type": "Reference",
      "definition": "Organization that issued/manages the identifier.",
      "referenceTypes": [
        "Organization"
      ]
    },
    {
      "name": "policyHolder",
      "path": "Coverage.policyHolder",
      "type": "Reference",
      "definition": "The party who 'owns' the insurance policy,  may be an individual, corporation or the subscriber's employer.",
      "referenceTypes": [
        "Patient",
        "RelatedPerson",
        "Organization"
      ]
    },
    {
      "name": "payor",
      "path": "Coverage.payor",
      "type": "Reference",
      "definition": "The program or plan underwriter or payor including both insurance and non-insurance agreements, such as patient-pay agreements. May provide multiple identifiers such as insurance company identifier or business identifier (BIN number).",
      "referenceTypes": [
        "Organization",
        "Patient",
        "RelatedPerson"
      ]
    },
    {
      "name": "assigner",
      "path": "Identifier.assigner",
      "type": "Reference",
      "definition": "Organization that issued/manages the identifier.",
      "referenceTypes": [
        "Organization"
      ]
    },
    {
      "name": "actor",
      "path": "DiagnosticReport.performer.actor",
      "type": "Reference",
      "definition": "The reference to the  practitioner or organization involved in producing the report. For example, the diagnostic service that is responsible for issuing the report.",
      "referenceTypes": [
        "Practitioner",
        "Organization"
      ]
    },
    {
      "name": "assigner",
      "path": "Identifier.assigner",
      "type": "Reference",
      "definition": "Organization that issued/manages the identifier.",
      "referenceTypes": [
        "Organization"
      ]
    },
    {
      "name": "assigner",
      "path": "Identifier.assigner",
      "type": "Reference",
      "definition": "Organization that issued/manages the identifier.",
      "referenceTypes": [
        "Organization"
      ]
    },
    {
      "name": "serviceProvider",
      "path": "Encounter.serviceProvider",
      "type": "Reference",
      "definition": "An organization that is in charge of maintaining the information of this Encounter (e.g. who maintains the report or the master service catalog item, etc.). This MAY be the same as the organization on the Patient record, however it could be different. This MAY not be not the Service Delivery Location's Organization.",
      "referenceTypes": [
        "Organization"
      ]
    },
    {
      "name": "assigner",
      "path": "Identifier.assigner",
      "type": "Reference",
      "definition": "Organization that issued/manages the identifier.",
      "referenceTypes": [
        "Organization"
      ]
    },
    {
      "name": "insurer",
      "path": "ExplanationOfBenefit.insurer",
      "type": "Reference",
      "definition": "The insurer which is responsible for the explanation of benefit.",
      "referenceTypes": [
        "Organization"
      ]
    },
    {
      "name": "organization",
      "path": "ExplanationOfBenefit.organization",
      "type": "Reference",
      "definition": "The provider which is responsible for the claim.",
      "referenceTypes": [
        "Organization"
      ]
    },
    {
      "name": "assigner",
      "path": "Identifier.assigner",
      "type": "Reference",
      "definition": "Organization that issued/manages the identifier.",
      "referenceTypes": [
        "Organization"
      ]
    },
    {
      "name": "party",
      "path": "ExplanationOfBenefit.payee.party",
      "type": "Reference",
      "definition": "Party to be reimbursed: Subscriber, provider, other.",
      "referenceTypes": [
        "Practitioner",
        "Organization",
        "Patient",
        "RelatedPerson"
      ]
    },
    {
      "name": "provider",
      "path": "ExplanationOfBenefit.careTeam.provider",
      "type": "Reference",
      "definition": "The members of the team who provided the overall service.",
      "referenceTypes": [
        "Practitioner",
        "Organization"
      ]
    },
    {
      "name": "assigner",
      "path": "Identifier.assigner",
      "type": "Reference",
      "definition": "Organization that issued/manages the identifier.",
      "referenceTypes": [
        "Organization"
      ]
    },
    {
      "name": "assigner",
      "path": "Identifier.assigner",
      "type": "Reference",
      "definition": "Organization that issued/manages the identifier.",
      "referenceTypes": [
        "Organization"
      ]
    },
    {
      "name": "assigner",
      "path": "Identifier.assigner",
      "type": "Reference",
      "definition": "Organization that issued/manages the identifier.",
      "referenceTypes": [
        "Organization"
      ]
    },
    {
      "name": "assigner",
      "path": "Identifier.assigner",
      "type": "Reference",
      "definition": "Organization that issued/manages the identifier.",
      "referenceTypes": [
        "Organization"
      ]
    },
    {
      "name": "manufacturer",
      "path": "Immunization.manufacturer",
      "type": "Reference",
      "definition": "Name of vaccine manufacturer.",
      "referenceTypes": [
        "Organization"
      ]
    },
    {
      "name": "authority",
      "path": "Immunization.vaccinationProtocol.authority",
      "type": "Reference",
      "definition": "Indicates the authority who published the protocol.  E.g. ACIP.",
      "referenceTypes": [
        "Organization"
      ]
    },
    {
      "name": "assigner",
      "path": "Identifier.assigner",
      "type": "Reference",
      "definition": "Organization that issued/manages the identifier.",
      "referenceTypes": [
        "Organization"
      ]
    },
    {
      "name": "assigner",
      "path": "Identifier.assigner",
      "type": "Reference",
      "definition": "Organization that issued/manages the identifier.",
      "referenceTypes": [
        "Organization"
      ]
    },
    {
      "name": "agent",
      "path": "MedicationRequest.requester.agent",
      "type": "Reference",
      "definition": "The healthcare professional responsible for authorizing the initial prescription.",
      "referenceTypes": [
        "Practitioner",
        "Organization",
        "Patient",
        "RelatedPerson",
        "Device"
      ]
    },
    {
      "name": "onBehalfOf",
      "path": "MedicationRequest.requester.onBehalfOf",
      "type": "Reference",
      "definition": "The organization the device or practitioner was acting on behalf of.",
      "referenceTypes": [
        "Organization"
      ]
    },
    {
      "name": "performer",
      "path": "MedicationRequest.dispenseRequest.performer",
      "type": "Reference",
      "definition": "Indicates the intended dispensing Organization specified by the prescriber.",
      "referenceTypes": [
        "Organization"
      ]
    },
    {
      "name": "assigner",
      "path": "Identifier.assigner",
      "type": "Reference",
      "definition": "Organization that issued/manages the identifier.",
      "referenceTypes": [
        "Organization"
      ]
    },
    {
      "name": "performer",
      "path": "Observation.performer",
      "type": "Reference",
      "definition": "Who was responsible for asserting the observed value as \"true\".",
      "referenceTypes": [
        "Practitioner",
        "Organization",
        "Patient",
        "RelatedPerson"
      ]
    },
    {
      "name": "assigner",
      "path": "Identifier.assigner",
      "type": "Reference",
      "definition": "Organization that issued/manages the identifier.",
      "referenceTypes": [
        "Organization"
      ]
    },
    {
      "name": "organization",
      "path": "Patient.contact.organization",
      "type": "Reference",
      "definition": "Organization on behalf of which the contact is acting or for which the contact is working.",
      "referenceTypes": [
        "Organization"
      ]
    },
    {
      "name": "generalPractitioner",
      "path": "Patient.generalPractitioner",
      "type": "Reference",
      "definition": "Patient's nominated care provider.",
      "referenceTypes": [
        "Organization",
        "Practitioner"
      ]
    },
    {
      "name": "managingOrganization",
      "path": "Patient.managingOrganization",
      "type": "Reference",
      "definition": "Organization that is the custodian of the patient record.",
      "referenceTypes": [
        "Organization"
      ]
    },
    {
      "name": "assigner",
      "path": "Identifier.assigner",
      "type": "Reference",
      "definition": "Organization that issued/manages the identifier.",
      "referenceTypes": [
        "Organization"
      ]
    },
    {
      "name": "assigner",
      "path": "Identifier.assigner",
      "type": "Reference",
      "definition": "Organization that issued/manages the identifier.",
      "referenceTypes": [
        "Organization"
      ]
    },
    {
      "name": "agent",
      "path": "ProcedureRequest.requester.agent",
      "type": "Reference",
      "definition": "The device, practitioner or organization who initiated the request.",
      "referenceTypes": [
        "Device",
        "Practitioner",
        "Organization"
      ]
    },
    {
      "name": "onBehalfOf",
      "path": "ProcedureRequest.requester.onBehalfOf",
      "type": "Reference",
      "definition": "The organization the device or practitioner was acting on behalf of.",
      "referenceTypes": [
        "Organization"
      ]
    },
    {
      "name": "performer",
      "path": "ProcedureRequest.performer",
      "type": "Reference",
      "definition": "The desired perfomer for doing the diagnostic testing.  For example, the surgeon, dermatopathologist, endoscopist, etc.",
      "referenceTypes": [
        "Practitioner",
        "Organization",
        "Patient",
        "Device",
        "RelatedPerson",
        "HealthcareService"
      ]
    }
  ],
  "Patient": [
    {
      "name": "patient",
      "path": "AllergyIntolerance.patient",
      "type": "Reference",
      "definition": "The patient who has the allergy or intolerance.",
      "referenceTypes": [
        "Patient"
      ]
    },
    {
      "name": "recorder",
      "path": "AllergyIntolerance.recorder",
      "type": "Reference",
      "definition": "Individual who recorded the record and takes responsibility for its content.",
      "referenceTypes": [
        "Practitioner",
        "Patient"
      ]
    },
    {
      "name": "asserter",
      "path": "AllergyIntolerance.asserter",
      "type": "Reference",
      "definition": "The source of the information about the allergy that is recorded.",
      "referenceTypes": [
        "Patient",
        "RelatedPerson",
        "Practitioner"
      ]
    },
    {
      "name": "authorReference",
      "path": "Annotation.authorReference",
      "type": "Reference",
      "definition": "The individual responsible for making the annotation.",
      "referenceTypes": [
        "Practitioner",
        "Patient",
        "RelatedPerson"
      ]
    },
    {
      "name": "authorReference",
      "path": "Annotation.authorReference",
      "type": "Reference",
      "definition": "The individual responsible for making the annotation.",
      "referenceTypes": [
        "Practitioner",
        "Patient",
        "RelatedPerson"
      ]
    },
    {
      "name": "subject",
      "path": "CarePlan.subject",
      "type": "Reference",
      "definition": "Identifies the patient or group whose intended care is described by the plan.",
      "referenceTypes": [
        "Patient",
        "Group"
      ]
    },
    {
      "name": "author",
      "path": "CarePlan.author",
      "type": "Reference",
      "definition": "Identifies the individual(s) or ogranization who is responsible for the content of the care plan.",
      "referenceTypes": [
        "Patient",
        "Practitioner",
        "RelatedPerson",
        "Organization",
        "CareTeam"
      ]
    },
    {
      "name": "authorReference",
      "path": "Annotation.authorReference",
      "type": "Reference",
      "definition": "The individual responsible for making the annotation.",
      "referenceTypes": [
        "Practitioner",
        "Patient",
        "RelatedPerson"
      ]
    },
    {
      "name": "performer",
      "path": "CarePlan.activity.detail.performer",
      "type": "Reference",
      "definition": "Identifies who's expected to be involved in the activity.",
      "referenceTypes": [
        "Practitioner",
        "Organization",
        "RelatedPerson",
        "Patient",
        "CareTeam"
      ]
    },
    {
      "name": "authorReference",
      "path": "Annotation.authorReference",
      "type": "Reference",
      "definition": "The individual responsible for making the annotation.",
      "referenceTypes": [
        "Practitioner",
        "Patient",
        "RelatedPerson"
      ]
    },
    {
      "name": "patient",
      "path": "Claim.patient",
      "type": "Reference",
      "definition": "Patient Resource.",
      "referenceTypes": [
        "Patient"
      ]
    },
    {
      "name": "party",
      "path": "Claim.payee.party",
      "type": "Reference",
      "definition": "Party to be reimbursed: Subscriber, provider, other.",
      "referenceTypes": [
        "Practitioner",
        "Organization",
        "Patient",
        "RelatedPerson"
      ]
    },
    {
      "name": "subject",
      "path": "Condition.subject",
      "type": "Reference",
      "definition": "Indicates the patient or group who the condition record is associated with.",
      "referenceTypes": [
        "Patient",
        "Group"
      ]
    },
    {
      "name": "asserter",
      "path": "Condition.asserter",
      "type": "Reference",
      "definition": "Individual who is making the condition statement.",
      "referenceTypes": [
        "Practitioner",
        "Patient",
        "RelatedPerson"
      ]
    },
    {
      "name": "authorReference",
      "path": "Annotation.authorReference",
      "type": "Reference",
      "definition": "The individual responsible for making the annotation.",
      "referenceTypes": [
        "Practitioner",
        "Patient",
        "RelatedPerson"
      ]
    },
    {
      "name": "policyHolder",
      "path": "Coverage.policyHolder",
      "type": "Reference",
      "definition": "The party who 'owns' the insurance policy,  may be an individual, corporation or the subscriber's employer.",
      "referenceTypes": [
        "Patient",
        "RelatedPerson",
        "Organization"
      ]
    },
    {
      "name": "subscriber",
      "path": "Coverage.subscriber",
      "type": "Reference",
      "definition": "The party who has signed-up for or 'owns' the contractual relationship to the policy or to whom the benefit of the policy for services rendered to them or their family is due.",
      "referenceTypes": [
        "Patient",
        "RelatedPerson"
      ]
    },
    {
      "name": "beneficiary",
      "path": "Coverage.beneficiary",
      "type": "Reference",
      "definition": "The party who benefits from the insurance coverage., the patient when services are provided.",
      "referenceTypes": [
        "Patient"
      ]
    },
    {
      "name": "payor",
      "path": "Coverage.payor",
      "type": "Reference",
      "definition": "The program or plan underwriter or payor including both insurance and non-insurance agreements, such as patient-pay agreements. May provide multiple identifiers such as insurance company identifier or business identifier (BIN number).",
      "referenceTypes": [
        "Organization",
        "Patient",
        "RelatedPerson"
      ]
    },
    {
      "name": "subject",
      "path": "DiagnosticReport.subject",
      "type": "Reference",
      "definition": "The subject of the report. Usually, but not always, this is a patient. However diagnostic services also perform analyses on specimens collected from a variety of other sources.",
      "referenceTypes": [
        "Patient",
        "Group",
        "Device",
        "Location"
      ]
    },
    {
      "name": "subject",
      "path": "Encounter.subject",
      "type": "Reference",
      "definition": "The patient ro group present at the encounter.",
      "referenceTypes": [
        "Patient",
        "Group"
      ]
    },
    {
      "name": "patient",
      "path": "ExplanationOfBenefit.patient",
      "type": "Reference",
      "definition": "Patient Resource.",
      "referenceTypes": [
        "Patient"
      ]
    },
    {
      "name": "party",
      "path": "ExplanationOfBenefit.payee.party",
      "type": "Reference",
      "definition": "Party to be reimbursed: Subscriber, provider, other.",
      "referenceTypes": [
        "Practitioner",
        "Organization",
        "Patient",
        "RelatedPerson"
      ]
    },
    {
      "name": "patient",
      "path": "ImagingStudy.patient",
      "type": "Reference",
      "definition": "The patient imaged in the study.",
      "referenceTypes": [
        "Patient"
      ]
    },
    {
      "name": "patient",
      "path": "Immunization.patient",
      "type": "Reference",
      "definition": "The patient who either received or did not receive the immunization.",
      "referenceTypes": [
        "Patient"
      ]
    },
    {
      "name": "authorReference",
      "path": "Annotation.authorReference",
      "type": "Reference",
      "definition": "The individual responsible for making the annotation.",
      "referenceTypes": [
        "Practitioner",
        "Patient",
        "RelatedPerson"
      ]
    },
    {
      "name": "subject",
      "path": "MedicationRequest.subject",
      "type": "Reference",
      "definition": "A link to a resource representing the person or set of individuals to whom the medication will be given.",
      "referenceTypes": [
        "Patient",
        "Group"
      ]
    },
    {
      "name": "agent",
      "path": "MedicationRequest.requester.agent",
      "type": "Reference",
      "definition": "The healthcare professional responsible for authorizing the initial prescription.",
      "referenceTypes": [
        "Practitioner",
        "Organization",
        "Patient",
        "RelatedPerson",
        "Device"
      ]
    },
    {
      "name": "authorReference",
      "path": "Annotation.authorReference",
      "type": "Reference",
      "definition": "The individual responsible for making the annotation.",
      "referenceTypes": [
        "Practitioner",
        "Patient",
        "RelatedPerson"
      ]
    },
    {
      "name": "subject",
      "path": "Observation.subject",
      "type": "Reference",
      "definition": "The patient, or group of patients, location, or device whose characteristics (direct or indirect) are described by the observation and into whose record the observation is placed.  Comments: Indirect characteristics may be those of a specimen, fetus, donor,  other observer (for example a relative or EMT), or any observation made about the subject.",
      "referenceTypes": [
        "Patient",
        "Group",
        "Device",
        "Location"
      ]
    },
    {
      "name": "performer",
      "path": "Observation.performer",
      "type": "Reference",
      "definition": "Who was responsible for asserting the observed value as \"true\".",
      "referenceTypes": [
        "Practitioner",
        "Organization",
        "Patient",
        "RelatedPerson"
      ]
    },
    {
      "name": "other",
      "path": "Patient.link.other",
      "type": "Reference",
      "definition": "The other patient resource that the link refers to.",
      "referenceTypes": [
        "Patient",
        "RelatedPerson"
      ]
    },
    {
      "name": "subject",
      "path": "ProcedureRequest.subject",
      "type": "Reference",
      "definition": "On whom or what the procedure or diagnostic is to be performed. This is usually a human patient, but can also be requested on animals, groups of humans or animals, devices such as dialysis machines, or even locations (typically for environmental scans).",
      "referenceTypes": [
        "Patient",
        "Group",
        "Location",
        "Device"
      ]
    },
    {
      "name": "performer",
      "path": "ProcedureRequest.performer",
      "type": "Reference",
      "definition": "The desired perfomer for doing the diagnostic testing.  For example, the surgeon, dermatopathologist, endoscopist, etc.",
      "referenceTypes": [
        "Practitioner",
        "Organization",
        "Patient",
        "Device",
        "RelatedPerson",
        "HealthcareService"
      ]
    },
    {
      "name": "authorReference",
      "path": "Annotation.authorReference",
      "type": "Reference",
      "definition": "The individual responsible for making the annotation.",
      "referenceTypes": [
        "Practitioner",
        "Patient",
        "RelatedPerson"
      ]
    }
  ],
  "Practitioner": [
    {
      "name": "recorder",
      "path": "AllergyIntolerance.recorder",
      "type": "Reference",
      "definition": "Individual who recorded the record and takes responsibility for its content.",
      "referenceTypes": [
        "Practitioner",
        "Patient"
      ]
    },
    {
      "name": "asserter",
      "path": "AllergyIntolerance.asserter",
      "type": "Reference",
      "definition": "The source of the information about the allergy that is recorded.",
      "referenceTypes": [
        "Patient",
        "RelatedPerson",
        "Practitioner"
      ]
    },
    {
      "name": "authorReference",
      "path": "Annotation.authorReference",
      "type": "Reference",
      "definition": "The individual responsible for making the annotation.",
      "referenceTypes": [
        "Practitioner",
        "Patient",
        "RelatedPerson"
      ]
    },
    {
      "name": "authorReference",
      "path": "Annotation.authorReference",
      "type": "Reference",
      "definition": "The individual responsible for making the annotation.",
      "referenceTypes": [
        "Practitioner",
        "Patient",
        "RelatedPerson"
      ]
    },
    {
      "name": "author",
      "path": "CarePlan.author",
      "type": "Reference",
      "definition": "Identifies the individual(s) or ogranization who is responsible for the content of the care plan.",
      "referenceTypes": [
        "Patient",
        "Practitioner",
        "RelatedPerson",
        "Organization",
        "CareTeam"
      ]
    },
    {
      "name": "authorReference",
      "path": "Annotation.authorReference",
      "type": "Reference",
      "definition": "The individual responsible for making the annotation.",
      "referenceTypes": [
        "Practitioner",
        "Patient",
        "RelatedPerson"
      ]
    },
    {
      "name": "performer",
      "path": "CarePlan.activity.detail.performer",
      "type": "Reference",
      "definition": "Identifies who's expected to be involved in the activity.",
      "referenceTypes": [
        "Practitioner",
        "Organization",
        "RelatedPerson",
        "Patient",
        "CareTeam"
      ]
    },
    {
      "name": "authorReference",
      "path": "Annotation.authorReference",
      "type": "Reference",
      "definition": "The individual responsible for making the annotation.",
      "referenceTypes": [
        "Practitioner",
        "Patient",
        "RelatedPerson"
      ]
    },
    {
      "name": "enterer",
      "path": "Claim.enterer",
      "type": "Reference",
      "definition": "Person who created the invoice/claim/pre-determination or pre-authorization.",
      "referenceTypes": [
        "Practitioner"
      ]
    },
    {
      "name": "provider",
      "path": "Claim.provider",
      "type": "Reference",
      "definition": "The provider which is responsible for the bill, claim pre-determination, pre-authorization.",
      "referenceTypes": [
        "Practitioner"
      ]
    },
    {
      "name": "party",
      "path": "Claim.payee.party",
      "type": "Reference",
      "definition": "Party to be reimbursed: Subscriber, provider, other.",
      "referenceTypes": [
        "Practitioner",
        "Organization",
        "Patient",
        "RelatedPerson"
      ]
    },
    {
      "name": "provider",
      "path": "Claim.careTeam.provider",
      "type": "Reference",
      "definition": "Member of the team who provided the overall service.",
      "referenceTypes": [
        "Practitioner",
        "Organization"
      ]
    },
    {
      "name": "asserter",
      "path": "Condition.asserter",
      "type": "Reference",
      "definition": "Individual who is making the condition statement.",
      "referenceTypes": [
        "Practitioner",
        "Patient",
        "RelatedPerson"
      ]
    },
    {
      "name": "authorReference",
      "path": "Annotation.authorReference",
      "type": "Reference",
      "definition": "The individual responsible for making the annotation.",
      "referenceTypes": [
        "Practitioner",
        "Patient",
        "RelatedPerson"
      ]
    },
    {
      "name": "actor",
      "path": "DiagnosticReport.performer.actor",
      "type": "Reference",
      "definition": "The reference to the  practitioner or organization involved in producing the report. For example, the diagnostic service that is responsible for issuing the report.",
      "referenceTypes": [
        "Practitioner",
        "Organization"
      ]
    },
    {
      "name": "individual",
      "path": "Encounter.participant.individual",
      "type": "Reference",
      "definition": "Persons involved in the encounter other than the patient.",
      "referenceTypes": [
        "Practitioner",
        "RelatedPerson"
      ]
    },
    {
      "name": "enterer",
      "path": "ExplanationOfBenefit.enterer",
      "type": "Reference",
      "definition": "The person who created the explanation of benefit.",
      "referenceTypes": [
        "Practitioner"
      ]
    },
    {
      "name": "provider",
      "path": "ExplanationOfBenefit.provider",
      "type": "Reference",
      "definition": "The provider which is responsible for the claim.",
      "referenceTypes": [
        "Practitioner"
      ]
    },
    {
      "name": "party",
      "path": "ExplanationOfBenefit.payee.party",
      "type": "Reference",
      "definition": "Party to be reimbursed: Subscriber, provider, other.",
      "referenceTypes": [
        "Practitioner",
        "Organization",
        "Patient",
        "RelatedPerson"
      ]
    },
    {
      "name": "provider",
      "path": "ExplanationOfBenefit.careTeam.provider",
      "type": "Reference",
      "definition": "The members of the team who provided the overall service.",
      "referenceTypes": [
        "Practitioner",
        "Organization"
      ]
    },
    {
      "name": "referrer",
      "path": "ImagingStudy.referrer",
      "type": "Reference",
      "definition": "The requesting/referring physician.",
      "referenceTypes": [
        "Practitioner"
      ]
    },
    {
      "name": "interpreter",
      "path": "ImagingStudy.interpreter",
      "type": "Reference",
      "definition": "Who read the study and interpreted the images or other content.",
      "referenceTypes": [
        "Practitioner"
      ]
    },
    {
      "name": "performer",
      "path": "ImagingStudy.series.performer",
      "type": "Reference",
      "definition": "The physician or operator (often the radiology technician)  who performed the series. The performer is recorded at the series level, since each series in a study may be performed by a different practitioner, at different times, and using different devices. A series may be performed by multiple practitioners.",
      "referenceTypes": [
        "Practitioner"
      ]
    },
    {
      "name": "actor",
      "path": "Immunization.practitioner.actor",
      "type": "Reference",
      "definition": "The device, practitioner, etc. who performed the action.",
      "referenceTypes": [
        "Practitioner"
      ]
    },
    {
      "name": "authorReference",
      "path": "Annotation.authorReference",
      "type": "Reference",
      "definition": "The individual responsible for making the annotation.",
      "referenceTypes": [
        "Practitioner",
        "Patient",
        "RelatedPerson"
      ]
    },
    {
      "name": "agent",
      "path": "MedicationRequest.requester.agent",
      "type": "Reference",
      "definition": "The healthcare professional responsible for authorizing the initial prescription.",
      "referenceTypes": [
        "Practitioner",
        "Organization",
        "Patient",
        "RelatedPerson",
        "Device"
      ]
    },
    {
      "name": "recorder",
      "path": "MedicationRequest.recorder",
      "type": "Reference",
      "definition": "The person who entered the order on behalf of another individual for example in the case of a verbal or a telephone order.",
      "referenceTypes": [
        "Practitioner"
      ]
    },
    {
      "name": "authorReference",
      "path": "Annotation.authorReference",
      "type": "Reference",
      "definition": "The individual responsible for making the annotation.",
      "referenceTypes": [
        "Practitioner",
        "Patient",
        "RelatedPerson"
      ]
    },
    {
      "name": "performer",
      "path": "Observation.performer",
      "type": "Reference",
      "definition": "Who was responsible for asserting the observed value as \"true\".",
      "referenceTypes": [
        "Practitioner",
        "Organization",
        "Patient",
        "RelatedPerson"
      ]
    },
    {
      "name": "generalPractitioner",
      "path": "Patient.generalPractitioner",
      "type": "Reference",
      "definition": "Patient's nominated care provider.",
      "referenceTypes": [
        "Organization",
        "Practitioner"
      ]
    },
    {
      "name": "agent",
      "path": "ProcedureRequest.requester.agent",
      "type": "Reference",
      "definition": "The device, practitioner or organization who initiated the request.",
      "referenceTypes": [
        "Device",
        "Practitioner",
        "Organization"
      ]
    },
    {
      "name": "performer",
      "path": "ProcedureRequest.performer",
      "type": "Reference",
      "definition": "The desired perfomer for doing the diagnostic testing.  For example, the surgeon, dermatopathologist, endoscopist, etc.",
      "referenceTypes": [
        "Practitioner",
        "Organization",
        "Patient",
        "Device",
        "RelatedPerson",
        "HealthcareService"
      ]
    },
    {
      "name": "authorReference",
      "path": "Annotation.authorReference",
      "type": "Reference",
      "definition": "The individual responsible for making the annotation.",
      "referenceTypes": [
        "Practitioner",
        "Patient",
        "RelatedPerson"
      ]
    }
  ],
  "RelatedPerson": [
    {
      "name": "asserter",
      "path": "AllergyIntolerance.asserter",
      "type": "Reference",
      "definition": "The source of the information about the allergy that is recorded.",
      "referenceTypes": [
        "Patient",
        "RelatedPerson",
        "Practitioner"
      ]
    },
    {
      "name": "authorReference",
      "path": "Annotation.authorReference",
      "type": "Reference",
      "definition": "The individual responsible for making the annotation.",
      "referenceTypes": [
        "Practitioner",
        "Patient",
        "RelatedPerson"
      ]
    },
    {
      "name": "authorReference",
      "path": "Annotation.authorReference",
      "type": "Reference",
      "definition": "The individual responsible for making the annotation.",
      "referenceTypes": [
        "Practitioner",
        "Patient",
        "RelatedPerson"
      ]
    },
    {
      "name": "author",
      "path": "CarePlan.author",
      "type": "Reference",
      "definition": "Identifies the individual(s) or ogranization who is responsible for the content of the care plan.",
      "referenceTypes": [
        "Patient",
        "Practitioner",
        "RelatedPerson",
        "Organization",
        "CareTeam"
      ]
    },
    {
      "name": "authorReference",
      "path": "Annotation.authorReference",
      "type": "Reference",
      "definition": "The individual responsible for making the annotation.",
      "referenceTypes": [
        "Practitioner",
        "Patient",
        "RelatedPerson"
      ]
    },
    {
      "name": "performer",
      "path": "CarePlan.activity.detail.performer",
      "type": "Reference",
      "definition": "Identifies who's expected to be involved in the activity.",
      "referenceTypes": [
        "Practitioner",
        "Organization",
        "RelatedPerson",
        "Patient",
        "CareTeam"
      ]
    },
    {
      "name": "authorReference",
      "path": "Annotation.authorReference",
      "type": "Reference",
      "definition": "The individual responsible for making the annotation.",
      "referenceTypes": [
        "Practitioner",
        "Patient",
        "RelatedPerson"
      ]
    },
    {
      "name": "party",
      "path": "Claim.payee.party",
      "type": "Reference",
      "definition": "Party to be reimbursed: Subscriber, provider, other.",
      "referenceTypes": [
        "Practitioner",
        "Organization",
        "Patient",
        "RelatedPerson"
      ]
    },
    {
      "name": "asserter",
      "path": "Condition.asserter",
      "type": "Reference",
      "definition": "Individual who is making the condition statement.",
      "referenceTypes": [
        "Practitioner",
        "Patient",
        "RelatedPerson"
      ]
    },
    {
      "name": "authorReference",
      "path": "Annotation.authorReference",
      "type": "Reference",
      "definition": "The individual responsible for making the annotation.",
      "referenceTypes": [
        "Practitioner",
        "Patient",
        "RelatedPerson"
      ]
    },
    {
      "name": "policyHolder",
      "path": "Coverage.policyHolder",
      "type": "Reference",
      "definition": "The party who 'owns' the insurance policy,  may be an individual, corporation or the subscriber's employer.",
      "referenceTypes": [
        "Patient",
        "RelatedPerson",
        "Organization"
      ]
    },
    {
      "name": "subscriber",
      "path": "Coverage.subscriber",
      "type": "Reference",
      "definition": "The party who has signed-up for or 'owns' the contractual relationship to the policy or to whom the benefit of the policy for services rendered to them or their family is due.",
      "referenceTypes": [
        "Patient",
        "RelatedPerson"
      ]
    },
    {
      "name": "payor",
      "path": "Coverage.payor",
      "type": "Reference",
      "definition": "The program or plan underwriter or payor including both insurance and non-insurance agreements, such as patient-pay agreements. May provide multiple identifiers such as insurance company identifier or business identifier (BIN number).",
      "referenceTypes": [
        "Organization",
        "Patient",
        "RelatedPerson"
      ]
    },
    {
      "name": "individual",
      "path": "Encounter.participant.individual",
      "type": "Reference",
      "definition": "Persons involved in the encounter other than the patient.",
      "referenceTypes": [
        "Practitioner",
        "RelatedPerson"
      ]
    },
    {
      "name": "party",
      "path": "ExplanationOfBenefit.payee.party",
      "type": "Reference",
      "definition": "Party to be reimbursed: Subscriber, provider, other.",
      "referenceTypes": [
        "Practitioner",
        "Organization",
        "Patient",
        "RelatedPerson"
      ]
    },
    {
      "name": "authorReference",
      "path": "Annotation.authorReference",
      "type": "Reference",
      "definition": "The individual responsible for making the annotation.",
      "referenceTypes": [
        "Practitioner",
        "Patient",
        "RelatedPerson"
      ]
    },
    {
      "name": "agent",
      "path": "MedicationRequest.requester.agent",
      "type": "Reference",
      "definition": "The healthcare professional responsible for authorizing the initial prescription.",
      "referenceTypes": [
        "Practitioner",
        "Organization",
        "Patient",
        "RelatedPerson",
        "Device"
      ]
    },
    {
      "name": "authorReference",
      "path": "Annotation.authorReference",
      "type": "Reference",
      "definition": "The individual responsible for making the annotation.",
      "referenceTypes": [
        "Practitioner",
        "Patient",
        "RelatedPerson"
      ]
    },
    {
      "name": "performer",
      "path": "Observation.performer",
      "type": "Reference",
      "definition": "Who was responsible for asserting the observed value as \"true\".",
      "referenceTypes": [
        "Practitioner",
        "Organization",
        "Patient",
        "RelatedPerson"
      ]
    },
    {
      "name": "other",
      "path": "Patient.link.other",
      "type": "Reference",
      "definition": "The other patient resource that the link refers to.",
      "referenceTypes": [
        "Patient",
        "RelatedPerson"
      ]
    },
    {
      "name": "performer",
      "path": "ProcedureRequest.performer",
      "type": "Reference",
      "definition": "The desired perfomer for doing the diagnostic testing.  For example, the surgeon, dermatopathologist, endoscopist, etc.",
      "referenceTypes": [
        "Practitioner",
        "Organization",
        "Patient",
        "Device",
        "RelatedPerson",
        "HealthcareService"
      ]
    },
    {
      "name": "authorReference",
      "path": "Annotation.authorReference",
      "type": "Reference",
      "definition": "The individual responsible for making the annotation.",
      "referenceTypes": [
        "Practitioner",
        "Patient",
        "RelatedPerson"
      ]
    }
  ],
  "PlanDefinition": [
    {
      "name": "definition",
      "path": "CarePlan.definition",
      "type": "Reference",
      "definition": "Identifies the protocol, questionnaire, guideline or other specification the care plan should be conducted in accordance with.",
      "referenceTypes": [
        "PlanDefinition",
        "Questionnaire"
      ]
    },
    {
      "name": "definition",
      "path": "CarePlan.activity.detail.definition",
      "type": "Reference",
      "definition": "Identifies the protocol, questionnaire, guideline or other specification the planned activity should be conducted in accordance with.",
      "referenceTypes": [
        "PlanDefinition",
        "ActivityDefinition",
        "Questionnaire"
      ]
    },
    {
      "name": "definition",
      "path": "MedicationRequest.definition",
      "type": "Reference",
      "definition": "Protocol or definition followed by this request.",
      "referenceTypes": [
        "ActivityDefinition",
        "PlanDefinition"
      ]
    },
    {
      "name": "definition",
      "path": "ProcedureRequest.definition",
      "type": "Reference",
      "definition": "Protocol or definition followed by this request.",
      "referenceTypes": [
        "ActivityDefinition",
        "PlanDefinition"
      ]
    }
  ],
  "Questionnaire": [
    {
      "name": "definition",
      "path": "CarePlan.definition",
      "type": "Reference",
      "definition": "Identifies the protocol, questionnaire, guideline or other specification the care plan should be conducted in accordance with.",
      "referenceTypes": [
        "PlanDefinition",
        "Questionnaire"
      ]
    },
    {
      "name": "definition",
      "path": "CarePlan.activity.detail.definition",
      "type": "Reference",
      "definition": "Identifies the protocol, questionnaire, guideline or other specification the planned activity should be conducted in accordance with.",
      "referenceTypes": [
        "PlanDefinition",
        "ActivityDefinition",
        "Questionnaire"
      ]
    }
  ],
  "CarePlan": [
    {
      "name": "basedOn",
      "path": "CarePlan.basedOn",
      "type": "Reference",
      "definition": "A care plan that is fulfilled in whole or in part by this care plan.",
      "referenceTypes": [
        "CarePlan"
      ]
    },
    {
      "name": "replaces",
      "path": "CarePlan.replaces",
      "type": "Reference",
      "definition": "Completed or terminated care plan whose function is taken by this new care plan.",
      "referenceTypes": [
        "CarePlan"
      ]
    },
    {
      "name": "partOf",
      "path": "CarePlan.partOf",
      "type": "Reference",
      "definition": "A larger care plan of which this particular care plan is a component or step.",
      "referenceTypes": [
        "CarePlan"
      ]
    },
    {
      "name": "basedOn",
      "path": "DiagnosticReport.basedOn",
      "type": "Reference",
      "definition": "Details concerning a test or procedure requested.",
      "referenceTypes": [
        "CarePlan",
        "ImmunizationRecommendation",
        "MedicationRequest",
        "NutritionOrder",
        "ProcedureRequest",
        "ReferralRequest"
      ]
    },
    {
      "name": "basedOn",
      "path": "ImagingStudy.basedOn",
      "type": "Reference",
      "definition": "A list of the diagnostic requests that resulted in this imaging study being performed.",
      "referenceTypes": [
        "ReferralRequest",
        "CarePlan",
        "ProcedureRequest"
      ]
    },
    {
      "name": "basedOn",
      "path": "MedicationRequest.basedOn",
      "type": "Reference",
      "definition": "A plan or request that is fulfilled in whole or in part by this medication request.",
      "referenceTypes": [
        "CarePlan",
        "MedicationRequest",
        "ProcedureRequest",
        "ReferralRequest"
      ]
    },
    {
      "name": "basedOn",
      "path": "Observation.basedOn",
      "type": "Reference",
      "definition": "A plan, proposal or order that is fulfilled in whole or in part by this event.",
      "referenceTypes": [
        "CarePlan",
        "DeviceRequest",
        "ImmunizationRecommendation",
        "MedicationRequest",
        "NutritionOrder",
        "ProcedureRequest",
        "ReferralRequest"
      ]
    }
  ],
  "Group": [
    {
      "name": "subject",
      "path": "CarePlan.subject",
      "type": "Reference",
      "definition": "Identifies the patient or group whose intended care is described by the plan.",
      "referenceTypes": [
        "Patient",
        "Group"
      ]
    },
    {
      "name": "subject",
      "path": "Condition.subject",
      "type": "Reference",
      "definition": "Indicates the patient or group who the condition record is associated with.",
      "referenceTypes": [
        "Patient",
        "Group"
      ]
    },
    {
      "name": "subject",
      "path": "DiagnosticReport.subject",
      "type": "Reference",
      "definition": "The subject of the report. Usually, but not always, this is a patient. However diagnostic services also perform analyses on specimens collected from a variety of other sources.",
      "referenceTypes": [
        "Patient",
        "Group",
        "Device",
        "Location"
      ]
    },
    {
      "name": "subject",
      "path": "Encounter.subject",
      "type": "Reference",
      "definition": "The patient ro group present at the encounter.",
      "referenceTypes": [
        "Patient",
        "Group"
      ]
    },
    {
      "name": "subject",
      "path": "MedicationRequest.subject",
      "type": "Reference",
      "definition": "A link to a resource representing the person or set of individuals to whom the medication will be given.",
      "referenceTypes": [
        "Patient",
        "Group"
      ]
    },
    {
      "name": "subject",
      "path": "Observation.subject",
      "type": "Reference",
      "definition": "The patient, or group of patients, location, or device whose characteristics (direct or indirect) are described by the observation and into whose record the observation is placed.  Comments: Indirect characteristics may be those of a specimen, fetus, donor,  other observer (for example a relative or EMT), or any observation made about the subject.",
      "referenceTypes": [
        "Patient",
        "Group",
        "Device",
        "Location"
      ]
    },
    {
      "name": "subject",
      "path": "ProcedureRequest.subject",
      "type": "Reference",
      "definition": "On whom or what the procedure or diagnostic is to be performed. This is usually a human patient, but can also be requested on animals, groups of humans or animals, devices such as dialysis machines, or even locations (typically for environmental scans).",
      "referenceTypes": [
        "Patient",
        "Group",
        "Location",
        "Device"
      ]
    }
  ],
  "Encounter": [
    {
      "name": "context",
      "path": "CarePlan.context",
      "type": "Reference",
      "definition": "Identifies the original context in which this particular CarePlan was created.",
      "referenceTypes": [
        "Encounter",
        "EpisodeOfCare"
      ]
    },
    {
      "name": "encounter",
      "path": "Claim.item.encounter",
      "type": "Reference",
      "definition": "A billed item may include goods or services provided in multiple encounters.",
      "referenceTypes": [
        "Encounter"
      ]
    },
    {
      "name": "context",
      "path": "Condition.context",
      "type": "Reference",
      "definition": "Encounter during which the condition was first asserted.",
      "referenceTypes": [
        "Encounter",
        "EpisodeOfCare"
      ]
    },
    {
      "name": "context",
      "path": "DiagnosticReport.context",
      "type": "Reference",
      "definition": "The healthcare event  (e.g. a patient and healthcare provider interaction) which this DiagnosticReport per is about.",
      "referenceTypes": [
        "Encounter",
        "EpisodeOfCare"
      ]
    },
    {
      "name": "partOf",
      "path": "Encounter.partOf",
      "type": "Reference",
      "definition": "Another Encounter of which this encounter is a part of (administratively or in time).",
      "referenceTypes": [
        "Encounter"
      ]
    },
    {
      "name": "encounter",
      "path": "ExplanationOfBenefit.item.encounter",
      "type": "Reference",
      "definition": "A billed item may include goods or services provided in multiple encounters.",
      "referenceTypes": [
        "Encounter"
      ]
    },
    {
      "name": "context",
      "path": "ImagingStudy.context",
      "type": "Reference",
      "definition": "The encounter or episode at which the request is initiated.",
      "referenceTypes": [
        "Encounter",
        "EpisodeOfCare"
      ]
    },
    {
      "name": "encounter",
      "path": "Immunization.encounter",
      "type": "Reference",
      "definition": "The visit or admission or other contact between patient and health care provider the immunization was performed as part of.",
      "referenceTypes": [
        "Encounter"
      ]
    },
    {
      "name": "context",
      "path": "MedicationRequest.context",
      "type": "Reference",
      "definition": "A link to an encounter, or episode of care, that identifies the particular occurrence or set occurrences of contact between patient and health care provider.",
      "referenceTypes": [
        "Encounter",
        "EpisodeOfCare"
      ]
    },
    {
      "name": "context",
      "path": "Observation.context",
      "type": "Reference",
      "definition": "The healthcare event  (e.g. a patient and healthcare provider interaction) during which this observation is made.",
      "referenceTypes": [
        "Encounter",
        "EpisodeOfCare"
      ]
    },
    {
      "name": "context",
      "path": "ProcedureRequest.context",
      "type": "Reference",
      "definition": "An encounter or episode of care that provides additional information about the healthcare context in which this request is made.",
      "referenceTypes": [
        "Encounter",
        "EpisodeOfCare"
      ]
    }
  ],
  "EpisodeOfCare": [
    {
      "name": "context",
      "path": "CarePlan.context",
      "type": "Reference",
      "definition": "Identifies the original context in which this particular CarePlan was created.",
      "referenceTypes": [
        "Encounter",
        "EpisodeOfCare"
      ]
    },
    {
      "name": "context",
      "path": "Condition.context",
      "type": "Reference",
      "definition": "Encounter during which the condition was first asserted.",
      "referenceTypes": [
        "Encounter",
        "EpisodeOfCare"
      ]
    },
    {
      "name": "context",
      "path": "DiagnosticReport.context",
      "type": "Reference",
      "definition": "The healthcare event  (e.g. a patient and healthcare provider interaction) which this DiagnosticReport per is about.",
      "referenceTypes": [
        "Encounter",
        "EpisodeOfCare"
      ]
    },
    {
      "name": "episodeOfCare",
      "path": "Encounter.episodeOfCare",
      "type": "Reference",
      "definition": "Where a specific encounter should be classified as a part of a specific episode(s) of care this field should be used. This association can facilitate grouping of related encounters together for a specific purpose, such as government reporting, issue tracking, association via a common problem.  The association is recorded on the encounter as these are typically created after the episode of care, and grouped on entry rather than editing the episode of care to append another encounter to it (the episode of care could span years).",
      "referenceTypes": [
        "EpisodeOfCare"
      ]
    },
    {
      "name": "context",
      "path": "ImagingStudy.context",
      "type": "Reference",
      "definition": "The encounter or episode at which the request is initiated.",
      "referenceTypes": [
        "Encounter",
        "EpisodeOfCare"
      ]
    },
    {
      "name": "context",
      "path": "MedicationRequest.context",
      "type": "Reference",
      "definition": "A link to an encounter, or episode of care, that identifies the particular occurrence or set occurrences of contact between patient and health care provider.",
      "referenceTypes": [
        "Encounter",
        "EpisodeOfCare"
      ]
    },
    {
      "name": "context",
      "path": "Observation.context",
      "type": "Reference",
      "definition": "The healthcare event  (e.g. a patient and healthcare provider interaction) during which this observation is made.",
      "referenceTypes": [
        "Encounter",
        "EpisodeOfCare"
      ]
    },
    {
      "name": "context",
      "path": "ProcedureRequest.context",
      "type": "Reference",
      "definition": "An encounter or episode of care that provides additional information about the healthcare context in which this request is made.",
      "referenceTypes": [
        "Encounter",
        "EpisodeOfCare"
      ]
    }
  ],
  "CareTeam": [
    {
      "name": "author",
      "path": "CarePlan.author",
      "type": "Reference",
      "definition": "Identifies the individual(s) or ogranization who is responsible for the content of the care plan.",
      "referenceTypes": [
        "Patient",
        "Practitioner",
        "RelatedPerson",
        "Organization",
        "CareTeam"
      ]
    },
    {
      "name": "careTeam",
      "path": "CarePlan.careTeam",
      "type": "Reference",
      "definition": "Identifies all people and organizations who are expected to be involved in the care envisioned by this plan.",
      "referenceTypes": [
        "CareTeam"
      ]
    },
    {
      "name": "performer",
      "path": "CarePlan.activity.detail.performer",
      "type": "Reference",
      "definition": "Identifies who's expected to be involved in the activity.",
      "referenceTypes": [
        "Practitioner",
        "Organization",
        "RelatedPerson",
        "Patient",
        "CareTeam"
      ]
    }
  ],
  "Condition": [
    {
      "name": "addresses",
      "path": "CarePlan.addresses",
      "type": "Reference",
      "definition": "Identifies the conditions/problems/concerns/diagnoses/etc. whose management and/or mitigation are handled by this plan.",
      "referenceTypes": [
        "Condition"
      ]
    },
    {
      "name": "reasonReference",
      "path": "CarePlan.activity.detail.reasonReference",
      "type": "Reference",
      "definition": "Provides the health condition(s) that drove the inclusion of this particular activity as part of the plan.",
      "referenceTypes": [
        "Condition"
      ]
    },
    {
      "name": "diagnosisReference",
      "path": "Claim.diagnosis.diagnosisReference",
      "type": "Reference",
      "definition": "The diagnosis.",
      "referenceTypes": [
        "Condition"
      ]
    },
    {
      "name": "condition",
      "path": "Encounter.diagnosis.condition",
      "type": "Reference",
      "definition": "Reason the encounter takes place, as specified using information from another resource. For admissions, this is the admission diagnosis. The indication will typically be a Condition (with other resources referenced in the evidence.detail), or a Procedure.",
      "referenceTypes": [
        "Condition",
        "Procedure"
      ]
    },
    {
      "name": "diagnosisReference",
      "path": "ExplanationOfBenefit.diagnosis.diagnosisReference",
      "type": "Reference",
      "definition": "The diagnosis.",
      "referenceTypes": [
        "Condition"
      ]
    },
    {
      "name": "reasonReference",
      "path": "MedicationRequest.reasonReference",
      "type": "Reference",
      "definition": "Condition or observation that supports why the medication was ordered.",
      "referenceTypes": [
        "Condition",
        "Observation"
      ]
    },
    {
      "name": "reasonReference",
      "path": "ProcedureRequest.reasonReference",
      "type": "Reference",
      "definition": "Indicates another resource that provides a justification for why this diagnostic investigation is being requested.   May relate to the resources referred to in supportingInformation.",
      "referenceTypes": [
        "Condition",
        "Observation"
      ]
    }
  ],
  "Resource": [
    {
      "name": "supportingInfo",
      "path": "CarePlan.supportingInfo",
      "type": "Reference",
      "definition": "Identifies portions of the patient's record that specifically influenced the formation of the plan.  These might include co-morbidities, recent procedures, limitations, recent assessments, etc.",
      "referenceTypes": [
        "Resource"
      ]
    },
    {
      "name": "outcomeReference",
      "path": "CarePlan.activity.outcomeReference",
      "type": "Reference",
      "definition": "Details of the outcome or action resulting from the activity.  The reference to an \"event\" resource, such as Procedure or Encounter or Observation, is the result/outcome of the activity itself.  The activity can be conveyed using CarePlan.activity.detail OR using the CarePlan.activity.reference (a reference to a request resource).",
      "referenceTypes": [
        "Resource"
      ]
    },
    {
      "name": "valueReference",
      "path": "Claim.information.valueReference",
      "type": "Reference",
      "definition": "Additional data or information such as resources, documents, images etc. including references to the data or the actual inclusion of the data.",
      "referenceTypes": [
        "Resource"
      ]
    },
    {
      "name": "detail",
      "path": "Condition.evidence.detail",
      "type": "Reference",
      "definition": "Links to other relevant information, including pathology reports.",
      "referenceTypes": [
        "Resource"
      ]
    },
    {
      "name": "valueReference",
      "path": "ExplanationOfBenefit.information.valueReference",
      "type": "Reference",
      "definition": "Additional data or information such as resources, documents, images etc. including references to the data or the actual inclusion of the data.",
      "referenceTypes": [
        "Resource"
      ]
    },
    {
      "name": "supportingInformation",
      "path": "MedicationRequest.supportingInformation",
      "type": "Reference",
      "definition": "Include additional information (for example, patient height and weight) that supports the ordering of the medication.",
      "referenceTypes": [
        "Resource"
      ]
    },
    {
      "name": "basedOn",
      "path": "ProcedureRequest.basedOn",
      "type": "Reference",
      "definition": "Plan/proposal/order fulfilled by this request.",
      "referenceTypes": [
        "Resource"
      ]
    },
    {
      "name": "replaces",
      "path": "ProcedureRequest.replaces",
      "type": "Reference",
      "definition": "The request takes the place of the referenced completed or terminated request(s).",
      "referenceTypes": [
        "Resource"
      ]
    },
    {
      "name": "supportingInfo",
      "path": "ProcedureRequest.supportingInfo",
      "type": "Reference",
      "definition": "Additional clinical information about the patient or specimen that may influence the procedure or diagnostics or their interpretations.     This information includes diagnosis, clinical findings and other observations.  In laboratory ordering these are typically referred to as \"ask at order entry questions (AOEs)\".  This includes observations explicitly requested by the producer (filler) to provide context or supporting information needed to complete the order. For example,  reporting the amount of inspired oxygen for blood gas measurements.",
      "referenceTypes": [
        "Resource"
      ]
    }
  ],
  "Goal": [
    {
      "name": "goal",
      "path": "CarePlan.goal",
      "type": "Reference",
      "definition": "Describes the intended objective(s) of carrying out the care plan.",
      "referenceTypes": [
        "Goal"
      ]
    },
    {
      "name": "goal",
      "path": "CarePlan.activity.detail.goal",
      "type": "Reference",
      "definition": "Internal reference that identifies the goals that this activity is intended to contribute towards meeting.",
      "referenceTypes": [
        "Goal"
      ]
    }
  ],
  "Appointment": [
    {
      "name": "reference",
      "path": "CarePlan.activity.reference",
      "type": "Reference",
      "definition": "The details of the proposed activity represented in a specific resource.",
      "referenceTypes": [
        "Appointment",
        "CommunicationRequest",
        "DeviceRequest",
        "MedicationRequest",
        "NutritionOrder",
        "Task",
        "ProcedureRequest",
        "ReferralRequest",
        "VisionPrescription",
        "RequestGroup"
      ]
    },
    {
      "name": "appointment",
      "path": "Encounter.appointment",
      "type": "Reference",
      "definition": "The appointment that scheduled this encounter.",
      "referenceTypes": [
        "Appointment"
      ]
    }
  ],
  "CommunicationRequest": [
    {
      "name": "reference",
      "path": "CarePlan.activity.reference",
      "type": "Reference",
      "definition": "The details of the proposed activity represented in a specific resource.",
      "referenceTypes": [
        "Appointment",
        "CommunicationRequest",
        "DeviceRequest",
        "MedicationRequest",
        "NutritionOrder",
        "Task",
        "ProcedureRequest",
        "ReferralRequest",
        "VisionPrescription",
        "RequestGroup"
      ]
    }
  ],
  "DeviceRequest": [
    {
      "name": "reference",
      "path": "CarePlan.activity.reference",
      "type": "Reference",
      "definition": "The details of the proposed activity represented in a specific resource.",
      "referenceTypes": [
        "Appointment",
        "CommunicationRequest",
        "DeviceRequest",
        "MedicationRequest",
        "NutritionOrder",
        "Task",
        "ProcedureRequest",
        "ReferralRequest",
        "VisionPrescription",
        "RequestGroup"
      ]
    },
    {
      "name": "basedOn",
      "path": "Observation.basedOn",
      "type": "Reference",
      "definition": "A plan, proposal or order that is fulfilled in whole or in part by this event.",
      "referenceTypes": [
        "CarePlan",
        "DeviceRequest",
        "ImmunizationRecommendation",
        "MedicationRequest",
        "NutritionOrder",
        "ProcedureRequest",
        "ReferralRequest"
      ]
    }
  ],
  "MedicationRequest": [
    {
      "name": "reference",
      "path": "CarePlan.activity.reference",
      "type": "Reference",
      "definition": "The details of the proposed activity represented in a specific resource.",
      "referenceTypes": [
        "Appointment",
        "CommunicationRequest",
        "DeviceRequest",
        "MedicationRequest",
        "NutritionOrder",
        "Task",
        "ProcedureRequest",
        "ReferralRequest",
        "VisionPrescription",
        "RequestGroup"
      ]
    },
    {
      "name": "prescription",
      "path": "Claim.prescription",
      "type": "Reference",
      "definition": "Prescription to support the dispensing of Pharmacy or Vision products.",
      "referenceTypes": [
        "MedicationRequest",
        "VisionPrescription"
      ]
    },
    {
      "name": "originalPrescription",
      "path": "Claim.originalPrescription",
      "type": "Reference",
      "definition": "Original prescription which has been superceded by this prescription to support the dispensing of pharmacy services, medications or products. For example, a physician may prescribe a medication which the pharmacy determines is contraindicated, or for which the patient has an intolerance, and therefor issues a new precription for an alternate medication which has the same theraputic intent. The prescription from the pharmacy becomes the 'prescription' and that from the physician becomes the 'original prescription'.",
      "referenceTypes": [
        "MedicationRequest"
      ]
    },
    {
      "name": "basedOn",
      "path": "DiagnosticReport.basedOn",
      "type": "Reference",
      "definition": "Details concerning a test or procedure requested.",
      "referenceTypes": [
        "CarePlan",
        "ImmunizationRecommendation",
        "MedicationRequest",
        "NutritionOrder",
        "ProcedureRequest",
        "ReferralRequest"
      ]
    },
    {
      "name": "prescription",
      "path": "ExplanationOfBenefit.prescription",
      "type": "Reference",
      "definition": "Prescription to support the dispensing of Pharmacy or Vision products.",
      "referenceTypes": [
        "MedicationRequest",
        "VisionPrescription"
      ]
    },
    {
      "name": "originalPrescription",
      "path": "ExplanationOfBenefit.originalPrescription",
      "type": "Reference",
      "definition": "Original prescription which has been superceded by this prescription to support the dispensing of pharmacy services, medications or products. For example, a physician may prescribe a medication which the pharmacy determines is contraindicated, or for which the patient has an intolerance, and therefor issues a new precription for an alternate medication which has the same theraputic intent. The prescription from the pharmacy becomes the 'prescription' and that from the physician becomes the 'original prescription'.",
      "referenceTypes": [
        "MedicationRequest"
      ]
    },
    {
      "name": "basedOn",
      "path": "MedicationRequest.basedOn",
      "type": "Reference",
      "definition": "A plan or request that is fulfilled in whole or in part by this medication request.",
      "referenceTypes": [
        "CarePlan",
        "MedicationRequest",
        "ProcedureRequest",
        "ReferralRequest"
      ]
    },
    {
      "name": "priorPrescription",
      "path": "MedicationRequest.priorPrescription",
      "type": "Reference",
      "definition": "A link to a resource representing an earlier order related order or prescription.",
      "referenceTypes": [
        "MedicationRequest"
      ]
    },
    {
      "name": "basedOn",
      "path": "Observation.basedOn",
      "type": "Reference",
      "definition": "A plan, proposal or order that is fulfilled in whole or in part by this event.",
      "referenceTypes": [
        "CarePlan",
        "DeviceRequest",
        "ImmunizationRecommendation",
        "MedicationRequest",
        "NutritionOrder",
        "ProcedureRequest",
        "ReferralRequest"
      ]
    }
  ],
  "NutritionOrder": [
    {
      "name": "reference",
      "path": "CarePlan.activity.reference",
      "type": "Reference",
      "definition": "The details of the proposed activity represented in a specific resource.",
      "referenceTypes": [
        "Appointment",
        "CommunicationRequest",
        "DeviceRequest",
        "MedicationRequest",
        "NutritionOrder",
        "Task",
        "ProcedureRequest",
        "ReferralRequest",
        "VisionPrescription",
        "RequestGroup"
      ]
    },
    {
      "name": "basedOn",
      "path": "DiagnosticReport.basedOn",
      "type": "Reference",
      "definition": "Details concerning a test or procedure requested.",
      "referenceTypes": [
        "CarePlan",
        "ImmunizationRecommendation",
        "MedicationRequest",
        "NutritionOrder",
        "ProcedureRequest",
        "ReferralRequest"
      ]
    },
    {
      "name": "basedOn",
      "path": "Observation.basedOn",
      "type": "Reference",
      "definition": "A plan, proposal or order that is fulfilled in whole or in part by this event.",
      "referenceTypes": [
        "CarePlan",
        "DeviceRequest",
        "ImmunizationRecommendation",
        "MedicationRequest",
        "NutritionOrder",
        "ProcedureRequest",
        "ReferralRequest"
      ]
    }
  ],
  "Task": [
    {
      "name": "reference",
      "path": "CarePlan.activity.reference",
      "type": "Reference",
      "definition": "The details of the proposed activity represented in a specific resource.",
      "referenceTypes": [
        "Appointment",
        "CommunicationRequest",
        "DeviceRequest",
        "MedicationRequest",
        "NutritionOrder",
        "Task",
        "ProcedureRequest",
        "ReferralRequest",
        "VisionPrescription",
        "RequestGroup"
      ]
    }
  ],
  "ProcedureRequest": [
    {
      "name": "reference",
      "path": "CarePlan.activity.reference",
      "type": "Reference",
      "definition": "The details of the proposed activity represented in a specific resource.",
      "referenceTypes": [
        "Appointment",
        "CommunicationRequest",
        "DeviceRequest",
        "MedicationRequest",
        "NutritionOrder",
        "Task",
        "ProcedureRequest",
        "ReferralRequest",
        "VisionPrescription",
        "RequestGroup"
      ]
    },
    {
      "name": "basedOn",
      "path": "DiagnosticReport.basedOn",
      "type": "Reference",
      "definition": "Details concerning a test or procedure requested.",
      "referenceTypes": [
        "CarePlan",
        "ImmunizationRecommendation",
        "MedicationRequest",
        "NutritionOrder",
        "ProcedureRequest",
        "ReferralRequest"
      ]
    },
    {
      "name": "basedOn",
      "path": "ImagingStudy.basedOn",
      "type": "Reference",
      "definition": "A list of the diagnostic requests that resulted in this imaging study being performed.",
      "referenceTypes": [
        "ReferralRequest",
        "CarePlan",
        "ProcedureRequest"
      ]
    },
    {
      "name": "basedOn",
      "path": "MedicationRequest.basedOn",
      "type": "Reference",
      "definition": "A plan or request that is fulfilled in whole or in part by this medication request.",
      "referenceTypes": [
        "CarePlan",
        "MedicationRequest",
        "ProcedureRequest",
        "ReferralRequest"
      ]
    },
    {
      "name": "basedOn",
      "path": "Observation.basedOn",
      "type": "Reference",
      "definition": "A plan, proposal or order that is fulfilled in whole or in part by this event.",
      "referenceTypes": [
        "CarePlan",
        "DeviceRequest",
        "ImmunizationRecommendation",
        "MedicationRequest",
        "NutritionOrder",
        "ProcedureRequest",
        "ReferralRequest"
      ]
    }
  ],
  "ReferralRequest": [
    {
      "name": "reference",
      "path": "CarePlan.activity.reference",
      "type": "Reference",
      "definition": "The details of the proposed activity represented in a specific resource.",
      "referenceTypes": [
        "Appointment",
        "CommunicationRequest",
        "DeviceRequest",
        "MedicationRequest",
        "NutritionOrder",
        "Task",
        "ProcedureRequest",
        "ReferralRequest",
        "VisionPrescription",
        "RequestGroup"
      ]
    },
    {
      "name": "referral",
      "path": "Claim.referral",
      "type": "Reference",
      "definition": "The referral resource which lists the date, practitioner, reason and other supporting information.",
      "referenceTypes": [
        "ReferralRequest"
      ]
    },
    {
      "name": "basedOn",
      "path": "DiagnosticReport.basedOn",
      "type": "Reference",
      "definition": "Details concerning a test or procedure requested.",
      "referenceTypes": [
        "CarePlan",
        "ImmunizationRecommendation",
        "MedicationRequest",
        "NutritionOrder",
        "ProcedureRequest",
        "ReferralRequest"
      ]
    },
    {
      "name": "incomingReferral",
      "path": "Encounter.incomingReferral",
      "type": "Reference",
      "definition": "The referral request this encounter satisfies (incoming referral).",
      "referenceTypes": [
        "ReferralRequest"
      ]
    },
    {
      "name": "referral",
      "path": "ExplanationOfBenefit.referral",
      "type": "Reference",
      "definition": "The referral resource which lists the date, practitioner, reason and other supporting information.",
      "referenceTypes": [
        "ReferralRequest"
      ]
    },
    {
      "name": "basedOn",
      "path": "ImagingStudy.basedOn",
      "type": "Reference",
      "definition": "A list of the diagnostic requests that resulted in this imaging study being performed.",
      "referenceTypes": [
        "ReferralRequest",
        "CarePlan",
        "ProcedureRequest"
      ]
    },
    {
      "name": "basedOn",
      "path": "MedicationRequest.basedOn",
      "type": "Reference",
      "definition": "A plan or request that is fulfilled in whole or in part by this medication request.",
      "referenceTypes": [
        "CarePlan",
        "MedicationRequest",
        "ProcedureRequest",
        "ReferralRequest"
      ]
    },
    {
      "name": "basedOn",
      "path": "Observation.basedOn",
      "type": "Reference",
      "definition": "A plan, proposal or order that is fulfilled in whole or in part by this event.",
      "referenceTypes": [
        "CarePlan",
        "DeviceRequest",
        "ImmunizationRecommendation",
        "MedicationRequest",
        "NutritionOrder",
        "ProcedureRequest",
        "ReferralRequest"
      ]
    }
  ],
  "VisionPrescription": [
    {
      "name": "reference",
      "path": "CarePlan.activity.reference",
      "type": "Reference",
      "definition": "The details of the proposed activity represented in a specific resource.",
      "referenceTypes": [
        "Appointment",
        "CommunicationRequest",
        "DeviceRequest",
        "MedicationRequest",
        "NutritionOrder",
        "Task",
        "ProcedureRequest",
        "ReferralRequest",
        "VisionPrescription",
        "RequestGroup"
      ]
    },
    {
      "name": "prescription",
      "path": "Claim.prescription",
      "type": "Reference",
      "definition": "Prescription to support the dispensing of Pharmacy or Vision products.",
      "referenceTypes": [
        "MedicationRequest",
        "VisionPrescription"
      ]
    },
    {
      "name": "prescription",
      "path": "ExplanationOfBenefit.prescription",
      "type": "Reference",
      "definition": "Prescription to support the dispensing of Pharmacy or Vision products.",
      "referenceTypes": [
        "MedicationRequest",
        "VisionPrescription"
      ]
    }
  ],
  "RequestGroup": [
    {
      "name": "reference",
      "path": "CarePlan.activity.reference",
      "type": "Reference",
      "definition": "The details of the proposed activity represented in a specific resource.",
      "referenceTypes": [
        "Appointment",
        "CommunicationRequest",
        "DeviceRequest",
        "MedicationRequest",
        "NutritionOrder",
        "Task",
        "ProcedureRequest",
        "ReferralRequest",
        "VisionPrescription",
        "RequestGroup"
      ]
    }
  ],
  "ActivityDefinition": [
    {
      "name": "definition",
      "path": "CarePlan.activity.detail.definition",
      "type": "Reference",
      "definition": "Identifies the protocol, questionnaire, guideline or other specification the planned activity should be conducted in accordance with.",
      "referenceTypes": [
        "PlanDefinition",
        "ActivityDefinition",
        "Questionnaire"
      ]
    },
    {
      "name": "definition",
      "path": "MedicationRequest.definition",
      "type": "Reference",
      "definition": "Protocol or definition followed by this request.",
      "referenceTypes": [
        "ActivityDefinition",
        "PlanDefinition"
      ]
    },
    {
      "name": "definition",
      "path": "ProcedureRequest.definition",
      "type": "Reference",
      "definition": "Protocol or definition followed by this request.",
      "referenceTypes": [
        "ActivityDefinition",
        "PlanDefinition"
      ]
    }
  ],
  "Location": [
    {
      "name": "location",
      "path": "CarePlan.activity.detail.location",
      "type": "Reference",
      "definition": "Identifies the facility where the activity will occur; e.g. home, hospital, specific clinic, etc.",
      "referenceTypes": [
        "Location"
      ]
    },
    {
      "name": "facility",
      "path": "Claim.facility",
      "type": "Reference",
      "definition": "Facility where the services were provided.",
      "referenceTypes": [
        "Location"
      ]
    },
    {
      "name": "locationReference",
      "path": "Claim.accident.locationReference",
      "type": "Reference",
      "definition": "Accident Place.",
      "referenceTypes": [
        "Location"
      ]
    },
    {
      "name": "locationReference",
      "path": "Claim.item.locationReference",
      "type": "Reference",
      "definition": "Where the service was provided.",
      "referenceTypes": [
        "Location"
      ]
    },
    {
      "name": "subject",
      "path": "DiagnosticReport.subject",
      "type": "Reference",
      "definition": "The subject of the report. Usually, but not always, this is a patient. However diagnostic services also perform analyses on specimens collected from a variety of other sources.",
      "referenceTypes": [
        "Patient",
        "Group",
        "Device",
        "Location"
      ]
    },
    {
      "name": "origin",
      "path": "Encounter.hospitalization.origin",
      "type": "Reference",
      "definition": "The location from which the patient came before admission.",
      "referenceTypes": [
        "Location"
      ]
    },
    {
      "name": "destination",
      "path": "Encounter.hospitalization.destination",
      "type": "Reference",
      "definition": "Location to which the patient is discharged.",
      "referenceTypes": [
        "Location"
      ]
    },
    {
      "name": "location",
      "path": "Encounter.location.location",
      "type": "Reference",
      "definition": "The location where the encounter takes place.",
      "referenceTypes": [
        "Location"
      ]
    },
    {
      "name": "facility",
      "path": "ExplanationOfBenefit.facility",
      "type": "Reference",
      "definition": "Facility where the services were provided.",
      "referenceTypes": [
        "Location"
      ]
    },
    {
      "name": "locationReference",
      "path": "ExplanationOfBenefit.accident.locationReference",
      "type": "Reference",
      "definition": "Where the accident occurred.",
      "referenceTypes": [
        "Location"
      ]
    },
    {
      "name": "locationReference",
      "path": "ExplanationOfBenefit.item.locationReference",
      "type": "Reference",
      "definition": "Where the service was provided.",
      "referenceTypes": [
        "Location"
      ]
    },
    {
      "name": "location",
      "path": "Immunization.location",
      "type": "Reference",
      "definition": "The service delivery location where the vaccine administration occurred.",
      "referenceTypes": [
        "Location"
      ]
    },
    {
      "name": "subject",
      "path": "Observation.subject",
      "type": "Reference",
      "definition": "The patient, or group of patients, location, or device whose characteristics (direct or indirect) are described by the observation and into whose record the observation is placed.  Comments: Indirect characteristics may be those of a specimen, fetus, donor,  other observer (for example a relative or EMT), or any observation made about the subject.",
      "referenceTypes": [
        "Patient",
        "Group",
        "Device",
        "Location"
      ]
    },
    {
      "name": "subject",
      "path": "ProcedureRequest.subject",
      "type": "Reference",
      "definition": "On whom or what the procedure or diagnostic is to be performed. This is usually a human patient, but can also be requested on animals, groups of humans or animals, devices such as dialysis machines, or even locations (typically for environmental scans).",
      "referenceTypes": [
        "Patient",
        "Group",
        "Location",
        "Device"
      ]
    }
  ],
  "Medication": [
    {
      "name": "productReference",
      "path": "CarePlan.activity.detail.productReference",
      "type": "Reference",
      "definition": "Identifies the food, drug or other product to be consumed or supplied in the activity.",
      "referenceTypes": [
        "Medication",
        "Substance"
      ]
    },
    {
      "name": "medicationReference",
      "path": "MedicationRequest.medicationReference",
      "type": "Reference",
      "definition": "Identifies the medication being requested. This is a link to a resource that represents the medication which may be the details of the medication or simply an attribute carrying a code that identifies the medication from a known list of medications.",
      "referenceTypes": [
        "Medication"
      ]
    }
  ],
  "Substance": [
    {
      "name": "productReference",
      "path": "CarePlan.activity.detail.productReference",
      "type": "Reference",
      "definition": "Identifies the food, drug or other product to be consumed or supplied in the activity.",
      "referenceTypes": [
        "Medication",
        "Substance"
      ]
    }
  ],
  "Claim": [
    {
      "name": "claim",
      "path": "Claim.related.claim",
      "type": "Reference",
      "definition": "Other claims which are related to this claim such as prior claim versions or for related services.",
      "referenceTypes": [
        "Claim"
      ]
    },
    {
      "name": "claim",
      "path": "ExplanationOfBenefit.claim",
      "type": "Reference",
      "definition": "The business identifier for the instance: invoice number, claim number, pre-determination or pre-authorization number.",
      "referenceTypes": [
        "Claim"
      ]
    },
    {
      "name": "claim",
      "path": "ExplanationOfBenefit.related.claim",
      "type": "Reference",
      "definition": "Other claims which are related to this claim such as prior claim versions or for related services.",
      "referenceTypes": [
        "Claim"
      ]
    }
  ],
  "Procedure": [
    {
      "name": "procedureReference",
      "path": "Claim.procedure.procedureReference",
      "type": "Reference",
      "definition": "The procedure code.",
      "referenceTypes": [
        "Procedure"
      ]
    },
    {
      "name": "condition",
      "path": "Encounter.diagnosis.condition",
      "type": "Reference",
      "definition": "Reason the encounter takes place, as specified using information from another resource. For admissions, this is the admission diagnosis. The indication will typically be a Condition (with other resources referenced in the evidence.detail), or a Procedure.",
      "referenceTypes": [
        "Condition",
        "Procedure"
      ]
    },
    {
      "name": "procedureReference",
      "path": "ExplanationOfBenefit.procedure.procedureReference",
      "type": "Reference",
      "definition": "The procedure code.",
      "referenceTypes": [
        "Procedure"
      ]
    },
    {
      "name": "procedureReference",
      "path": "ImagingStudy.procedureReference",
      "type": "Reference",
      "definition": "A reference to the performed Procedure.",
      "referenceTypes": [
        "Procedure"
      ]
    }
  ],
  "Coverage": [
    {
      "name": "coverage",
      "path": "Claim.insurance.coverage",
      "type": "Reference",
      "definition": "Reference to the program or plan identification, underwriter or payor.",
      "referenceTypes": [
        "Coverage"
      ]
    },
    {
      "name": "coverage",
      "path": "ExplanationOfBenefit.insurance.coverage",
      "type": "Reference",
      "definition": "Reference to the program or plan identification, underwriter or payor.",
      "referenceTypes": [
        "Coverage"
      ]
    }
  ],
  "ClaimResponse": [
    {
      "name": "claimResponse",
      "path": "Claim.insurance.claimResponse",
      "type": "Reference",
      "definition": "The Coverages adjudication details.",
      "referenceTypes": [
        "ClaimResponse"
      ]
    },
    {
      "name": "claimResponse",
      "path": "ExplanationOfBenefit.claimResponse",
      "type": "Reference",
      "definition": "The business identifier for the instance: invoice number, claim number, pre-determination or pre-authorization number.",
      "referenceTypes": [
        "ClaimResponse"
      ]
    }
  ],
  "Device": [
    {
      "name": "udi",
      "path": "Claim.item.udi",
      "type": "Reference",
      "definition": "List of Unique Device Identifiers associated with this line item.",
      "referenceTypes": [
        "Device"
      ]
    },
    {
      "name": "udi",
      "path": "Claim.item.detail.udi",
      "type": "Reference",
      "definition": "List of Unique Device Identifiers associated with this line item.",
      "referenceTypes": [
        "Device"
      ]
    },
    {
      "name": "udi",
      "path": "Claim.item.detail.subDetail.udi",
      "type": "Reference",
      "definition": "List of Unique Device Identifiers associated with this line item.",
      "referenceTypes": [
        "Device"
      ]
    },
    {
      "name": "subject",
      "path": "DiagnosticReport.subject",
      "type": "Reference",
      "definition": "The subject of the report. Usually, but not always, this is a patient. However diagnostic services also perform analyses on specimens collected from a variety of other sources.",
      "referenceTypes": [
        "Patient",
        "Group",
        "Device",
        "Location"
      ]
    },
    {
      "name": "udi",
      "path": "ExplanationOfBenefit.item.udi",
      "type": "Reference",
      "definition": "List of Unique Device Identifiers associated with this line item.",
      "referenceTypes": [
        "Device"
      ]
    },
    {
      "name": "udi",
      "path": "ExplanationOfBenefit.item.detail.udi",
      "type": "Reference",
      "definition": "List of Unique Device Identifiers associated with this line item.",
      "referenceTypes": [
        "Device"
      ]
    },
    {
      "name": "udi",
      "path": "ExplanationOfBenefit.item.detail.subDetail.udi",
      "type": "Reference",
      "definition": "List of Unique Device Identifiers associated with this line item.",
      "referenceTypes": [
        "Device"
      ]
    },
    {
      "name": "agent",
      "path": "MedicationRequest.requester.agent",
      "type": "Reference",
      "definition": "The healthcare professional responsible for authorizing the initial prescription.",
      "referenceTypes": [
        "Practitioner",
        "Organization",
        "Patient",
        "RelatedPerson",
        "Device"
      ]
    },
    {
      "name": "subject",
      "path": "Observation.subject",
      "type": "Reference",
      "definition": "The patient, or group of patients, location, or device whose characteristics (direct or indirect) are described by the observation and into whose record the observation is placed.  Comments: Indirect characteristics may be those of a specimen, fetus, donor,  other observer (for example a relative or EMT), or any observation made about the subject.",
      "referenceTypes": [
        "Patient",
        "Group",
        "Device",
        "Location"
      ]
    },
    {
      "name": "device",
      "path": "Observation.device",
      "type": "Reference",
      "definition": "The device used to generate the observation data.",
      "referenceTypes": [
        "Device",
        "DeviceMetric"
      ]
    },
    {
      "name": "subject",
      "path": "ProcedureRequest.subject",
      "type": "Reference",
      "definition": "On whom or what the procedure or diagnostic is to be performed. This is usually a human patient, but can also be requested on animals, groups of humans or animals, devices such as dialysis machines, or even locations (typically for environmental scans).",
      "referenceTypes": [
        "Patient",
        "Group",
        "Location",
        "Device"
      ]
    },
    {
      "name": "agent",
      "path": "ProcedureRequest.requester.agent",
      "type": "Reference",
      "definition": "The device, practitioner or organization who initiated the request.",
      "referenceTypes": [
        "Device",
        "Practitioner",
        "Organization"
      ]
    },
    {
      "name": "performer",
      "path": "ProcedureRequest.performer",
      "type": "Reference",
      "definition": "The desired perfomer for doing the diagnostic testing.  For example, the surgeon, dermatopathologist, endoscopist, etc.",
      "referenceTypes": [
        "Practitioner",
        "Organization",
        "Patient",
        "Device",
        "RelatedPerson",
        "HealthcareService"
      ]
    }
  ],
  "ClinicalImpression": [
    {
      "name": "assessment",
      "path": "Condition.stage.assessment",
      "type": "Reference",
      "definition": "Reference to a formal record of the evidence on which the staging assessment is based.",
      "referenceTypes": [
        "ClinicalImpression",
        "DiagnosticReport",
        "Observation"
      ]
    }
  ],
  "DiagnosticReport": [
    {
      "name": "assessment",
      "path": "Condition.stage.assessment",
      "type": "Reference",
      "definition": "Reference to a formal record of the evidence on which the staging assessment is based.",
      "referenceTypes": [
        "ClinicalImpression",
        "DiagnosticReport",
        "Observation"
      ]
    }
  ],
  "Observation": [
    {
      "name": "assessment",
      "path": "Condition.stage.assessment",
      "type": "Reference",
      "definition": "Reference to a formal record of the evidence on which the staging assessment is based.",
      "referenceTypes": [
        "ClinicalImpression",
        "DiagnosticReport",
        "Observation"
      ]
    },
    {
      "name": "result",
      "path": "DiagnosticReport.result",
      "type": "Reference",
      "definition": "Observations that are part of this diagnostic report. Observations can be simple name/value pairs (e.g. \"atomic\" results), or they can be grouping observations that include references to other members of the group (e.g. \"panels\").",
      "referenceTypes": [
        "Observation"
      ]
    },
    {
      "name": "detail",
      "path": "Immunization.reaction.detail",
      "type": "Reference",
      "definition": "Details of the reaction.",
      "referenceTypes": [
        "Observation"
      ]
    },
    {
      "name": "reasonReference",
      "path": "MedicationRequest.reasonReference",
      "type": "Reference",
      "definition": "Condition or observation that supports why the medication was ordered.",
      "referenceTypes": [
        "Condition",
        "Observation"
      ]
    },
    {
      "name": "target",
      "path": "Observation.related.target",
      "type": "Reference",
      "definition": "A reference to the observation or [QuestionnaireResponse](questionnaireresponse.html#) resource that is related to this observation.",
      "referenceTypes": [
        "Observation",
        "QuestionnaireResponse",
        "Sequence"
      ]
    },
    {
      "name": "reasonReference",
      "path": "ProcedureRequest.reasonReference",
      "type": "Reference",
      "definition": "Indicates another resource that provides a justification for why this diagnostic investigation is being requested.   May relate to the resources referred to in supportingInformation.",
      "referenceTypes": [
        "Condition",
        "Observation"
      ]
    }
  ],
  "Contract": [
    {
      "name": "contract",
      "path": "Coverage.contract",
      "type": "Reference",
      "definition": "The policy(s) which constitute this insurance coverage.",
      "referenceTypes": [
        "Contract"
      ]
    }
  ],
  "ImmunizationRecommendation": [
    {
      "name": "basedOn",
      "path": "DiagnosticReport.basedOn",
      "type": "Reference",
      "definition": "Details concerning a test or procedure requested.",
      "referenceTypes": [
        "CarePlan",
        "ImmunizationRecommendation",
        "MedicationRequest",
        "NutritionOrder",
        "ProcedureRequest",
        "ReferralRequest"
      ]
    },
    {
      "name": "basedOn",
      "path": "Observation.basedOn",
      "type": "Reference",
      "definition": "A plan, proposal or order that is fulfilled in whole or in part by this event.",
      "referenceTypes": [
        "CarePlan",
        "DeviceRequest",
        "ImmunizationRecommendation",
        "MedicationRequest",
        "NutritionOrder",
        "ProcedureRequest",
        "ReferralRequest"
      ]
    }
  ],
  "Specimen": [
    {
      "name": "specimen",
      "path": "DiagnosticReport.specimen",
      "type": "Reference",
      "definition": "Details about the specimens on which this diagnostic report is based.",
      "referenceTypes": [
        "Specimen"
      ]
    },
    {
      "name": "specimen",
      "path": "Observation.specimen",
      "type": "Reference",
      "definition": "The specimen that was used when this observation was made.",
      "referenceTypes": [
        "Specimen"
      ]
    },
    {
      "name": "specimen",
      "path": "ProcedureRequest.specimen",
      "type": "Reference",
      "definition": "One or more specimens that the laboratory procedure will use.",
      "referenceTypes": [
        "Specimen"
      ]
    }
  ],
  "ImagingStudy": [
    {
      "name": "imagingStudy",
      "path": "DiagnosticReport.imagingStudy",
      "type": "Reference",
      "definition": "One or more links to full details of any imaging performed during the diagnostic investigation. Typically, this is imaging performed by DICOM enabled modalities, but this is not required. A fully enabled PACS viewer can use this information to provide views of the source images.",
      "referenceTypes": [
        "ImagingStudy",
        "ImagingManifest"
      ]
    }
  ],
  "ImagingManifest": [
    {
      "name": "imagingStudy",
      "path": "DiagnosticReport.imagingStudy",
      "type": "Reference",
      "definition": "One or more links to full details of any imaging performed during the diagnostic investigation. Typically, this is imaging performed by DICOM enabled modalities, but this is not required. A fully enabled PACS viewer can use this information to provide views of the source images.",
      "referenceTypes": [
        "ImagingStudy",
        "ImagingManifest"
      ]
    }
  ],
  "Media": [
    {
      "name": "link",
      "path": "DiagnosticReport.image.link",
      "type": "Reference",
      "definition": "Reference to the image source.",
      "referenceTypes": [
        "Media"
      ]
    }
  ],
  "Account": [
    {
      "name": "account",
      "path": "Encounter.account",
      "type": "Reference",
      "definition": "The set of accounts that may be used for billing for this Encounter.",
      "referenceTypes": [
        "Account"
      ]
    }
  ],
  "Endpoint": [
    {
      "name": "endpoint",
      "path": "ImagingStudy.endpoint",
      "type": "Reference",
      "definition": "The network service providing access (e.g., query, view, or retrieval) for the study. See implementation notes for information about using DICOM endpoints. A study-level endpoint applies to each series in the study, unless overridden by a series-level endpoint with the same Endpoint.type.",
      "referenceTypes": [
        "Endpoint"
      ]
    },
    {
      "name": "endpoint",
      "path": "ImagingStudy.series.endpoint",
      "type": "Reference",
      "definition": "The network service providing access (e.g., query, view, or retrieval) for this series. See implementation notes for information about using DICOM endpoints. A series-level endpoint, if present, has precedence over a study-level endpoint with the same Endpoint.type.",
      "referenceTypes": [
        "Endpoint"
      ]
    }
  ],
  "DetectedIssue": [
    {
      "name": "detectedIssue",
      "path": "MedicationRequest.detectedIssue",
      "type": "Reference",
      "definition": "Indicates an actual or potential clinical issue with or between one or more active or proposed clinical actions for a patient; e.g. Drug-drug interaction, duplicate therapy, dosage alert etc.",
      "referenceTypes": [
        "DetectedIssue"
      ]
    }
  ],
  "Provenance": [
    {
      "name": "eventHistory",
      "path": "MedicationRequest.eventHistory",
      "type": "Reference",
      "definition": "Links to Provenance records for past versions of this resource or fulfilling request or event resources that identify key state transitions or updates that are likely to be relevant to a user looking at the current version of the resource.",
      "referenceTypes": [
        "Provenance"
      ]
    },
    {
      "name": "relevantHistory",
      "path": "ProcedureRequest.relevantHistory",
      "type": "Reference",
      "definition": "Key events in the history of the request.",
      "referenceTypes": [
        "Provenance"
      ]
    }
  ],
  "DeviceMetric": [
    {
      "name": "device",
      "path": "Observation.device",
      "type": "Reference",
      "definition": "The device used to generate the observation data.",
      "referenceTypes": [
        "Device",
        "DeviceMetric"
      ]
    }
  ],
  "QuestionnaireResponse": [
    {
      "name": "target",
      "path": "Observation.related.target",
      "type": "Reference",
      "definition": "A reference to the observation or [QuestionnaireResponse](questionnaireresponse.html#) resource that is related to this observation.",
      "referenceTypes": [
        "Observation",
        "QuestionnaireResponse",
        "Sequence"
      ]
    }
  ],
  "Sequence": [
    {
      "name": "target",
      "path": "Observation.related.target",
      "type": "Reference",
      "definition": "A reference to the observation or [QuestionnaireResponse](questionnaireresponse.html#) resource that is related to this observation.",
      "referenceTypes": [
        "Observation",
        "QuestionnaireResponse",
        "Sequence"
      ]
    }
  ],
  "HealthcareService": [
    {
      "name": "performer",
      "path": "ProcedureRequest.performer",
      "type": "Reference",
      "definition": "The desired perfomer for doing the diagnostic testing.  For example, the surgeon, dermatopathologist, endoscopist, etc.",
      "referenceTypes": [
        "Practitioner",
        "Organization",
        "Patient",
        "Device",
        "RelatedPerson",
        "HealthcareService"
      ]
    }
  ]
}